<Room>
  <Saves />
  <index>3C</index>
  <area>03</area>
  <x>27</x>
  <y>19</y>
  <width>08</width>
  <height>01</height>
  <upscroll>70</upscroll>
  <dnscroll>A0</dnscroll>
  <specialGFX>01</specialGFX>
  <Doors>
    <Door>
      <toroom area="03" index="3D" />
      <bitflag>00</bitflag>
      <direction>06</direction>
      <tilex>6</tilex>
      <tiley>4</tiley>
      <screenx>00</screenx>
      <screeny>00</screeny>
      <distance>02C0</distance>
      <doorcode>0000</doorcode>
    </Door>
    <Door>
      <toroom area="03" index="3B" />
      <bitflag>00</bitflag>
      <direction>07</direction>
      <tilex>6</tilex>
      <tiley>D</tiley>
      <screenx>00</screenx>
      <screeny>00</screeny>
      <distance>01C0</distance>
      <doorcode>0000</doorcode>
    </Door>
  </Doors>
  <States>
    <State condition="E740">
      <Arg>58</Arg>
      <Arg>39</Arg>
      <LevelData Width="8" Height="1">
        <Layer1>
          <Screen X="0" Y="0">
        8044 8044 8044 8044 8044 8044 8044 8044 8044 8044 8044 8044 8044 8044 8044 8044
        8160 8161 8162 8562 8563 8163 8162 8163 8162 8562 8563 8562 8563 8163 8162 8163
        8180 8181 8182 8582 8583 8183 8182 8183 8182 8582 8583 8582 85A3 8183 8182 8183
        8165 8166 0044 0044 09EE 09EF 0080 0080 0080 09EE 09EF 0080 02C7 0080 0080 0080
        8185 8186 0044 0044 0044 0044 0044 0044 0044 0044 0044 0044 02E7 0044 F118 F118
        8167 8168 0AEE 0AEF 0AEE 0AEF 0AEE 0AEF 0AEE 0AEF 0AEE 0AEF 02E8 0044 F118 F118
        8187 8188 02EC 02ED 02EC 02ED 02EC 02ED 02EC 02ED 02EC 02ED 8D84 8D83 8D82 8D83
        8165 8166 02EC 02ED 02EC 02ED 02EC 02ED 02EC 02ED 02EC 02ED 8D66 8D65 8D62 8D63
        8167 8168 02EE 02EF 02EE 02EF 02EE 02EF 02EE 02EF 02EE 02EF 8566 8565 8044 8044
        8187 8981 8983 8984 0080 01ED 0044 0044 0044 0044 02C0 02E3 8586 8585 8044 8044
        8586 8585 8965 8966 81FC 81FC C41D 541C 501C 501D 81FC 81FC 8568 8567 8044 8044
        8568 8567 8165 8166 8109 8129 9443 9442 9042 9043 8109 8109 8588 8587 8044 8044
        8588 8587 8185 8186 8109 8129 8463 8462 8062 8063 8129 8129 8566 8565 8044 8044
        8566 8565 8167 8168 8129 8109 8463 8462 8062 8063 8129 8109 8586 8585 8044 8044
        8586 8585 8187 8188 8129 8109 8463 8462 8062 8063 8109 8109 8568 8567 8044 8044
        8568 8567 8165 8166 8109 8109 8463 8462 8062 8063 8109 8109 8588 8587 8044 8044
      </Screen>
          <Screen X="1" Y="0">
        8044 8044 8044 8044 8044 8044 8044 8044 8044 8044 8044 8044 8044 8187 8188 856F
        8162 8163 8162 8562 8563 8163 8162 8163 8162 8163 8162 8562 8563 8165 8166 856F
        8182 81A3 8182 8582 8583 8183 8182 8183 8182 81A3 8182 8582 8583 8183 8184 8579
        0080 02C7 0044 0044 0044 0044 0044 0044 0044 02C7 0044 09EE 09EF 0044 0044 0044
        0044 02E7 0044 0044 0044 0044 0044 D044 0044 02E7 0044 0044 0044 0044 0044 0044
        F118 02E8 0AEF 0AEE 0AEF 0AEE 0AEF DAEE 0AEF 030A 0044 0044 0044 0044 0044 0044
        8983 8984 02ED 02EC 02ED 02EC 02ED D2EC 02ED 0329 0044 0044 0044 0044 0044 0044
        8965 8966 02ED 02EC 02ED 02EC 02ED D2EC 02ED 0309 0044 0044 0044 0044 0044 0044
        8165 8166 02EF 02EE 02EF 02EE 02EF D2EE 02EF 032A 0044 0044 0044 0044 0044 0044
        8185 8186 0044 0044 0044 0044 0044 D044 0044 02C7 0044 0044 0044 0044 0044 0080
        8167 8168 0044 0044 0044 0044 0044 D044 0044 02E8 0044 0044 0044 0044 0080 0080
        8187 8188 0044 0044 8D84 8D83 8983 8982 8983 8982 8D82 8D83 8983 8982 8983 8984
        8165 8166 0044 0044 8D66 8D65 8963 8962 8963 82C8 8D62 8D63 8963 8962 8965 8966
        8185 8186 0044 0044 8566 8565 8044 8044 8044 82E7 8044 8044 8044 8044 8165 8166
        8167 8168 0080 0080 8586 8585 8044 8044 8044 82C7 8044 8044 8044 8044 8185 8186
        8187 8188 8109 8109 8568 8567 8044 8044 8044 82E7 8044 8044 8044 8044 8167 8168
      </Screen>
          <Screen X="2" Y="0">
        816E 816E 816E 816F 8588 8587 8044 8044 8044 8044 8044 8044 8044 8044 8044 8044
        816E 816E 816E 816F 8566 8565 8562 8563 8562 8563 8163 8162 8163 8162 8562 8563
        8178 8178 8178 8179 8584 8583 8582 8583 8582 85A3 8183 8182 8183 8182 8582 8583
        8165 8100 A101 0044 0080 09EE 09EF 0044 0080 02C7 0080 0044 09EE 09EF 0044 0044
        8185 8120 A121 0044 0044 0044 0044 0044 0044 034A 0AEF 0AEE 0AEE 0AEF 0AEE 0AEF
        8165 8100 A101 0044 0044 0044 0044 0044 0044 0349 02ED 02EC 02EC 02ED 02EC 02ED
        8185 8120 A121 0044 0044 0044 0044 0044 0044 036A 02EF 02EE 02EE 02EF 02EE 02EF
        8165 8100 A101 0044 0044 0044 0044 0044 0044 036B 0AEF 0AEE 0AEE 0AEF 0AEE 0AEF
        8185 8120 A121 0044 0044 0044 0044 0044 0044 0369 02ED 02EC 02EC 02ED 02EC 02ED
        8165 8100 A101 0044 0080 02C2 0080 0044 0080 034B 02EF 02EE 02EE 02EF 02EE 02EF
        8185 8120 A121 0044 0044 02E2 0044 0044 0044 02E7 0044 0044 0044 0080 0044 0044
        8171 816B 856B 856A 805D 8169 8D84 8D83 8983 8982 8983 8982 8D82 8D83 8983 8982
        856F 816E 816E 8170 8978 8189 8D66 8D65 8963 82C8 8963 8962 8D62 8D63 8963 8962
        856F 816E 8970 816E 816E 816F 8566 8565 8044 82E7 8044 8044 8044 8044 8044 8044
        856F 816E 816E 816E 816E 816F 8586 8585 8044 82C7 8044 8044 8044 8044 8044 8044
        856F 816E 816E 816E 816E 816F 8568 8567 8044 82E7 8044 8044 8044 8044 8044 8044
      </Screen>
          <Screen X="3" Y="0">
        8044 8044 8044 8044 8185 8186 9C63 9C62 9862 9863 8588 8587 8044 8044 8044 8044
        8163 8162 8562 8563 8165 8166 2C43 2C42 2842 2843 8566 8565 8562 8563 8562 8563
        8183 8182 8582 8583 8183 8184 CC1D 5C1C 581C 581D 8584 8583 8582 85A3 8582 8583
        0044 0044 0044 0044 0044 0044 0044 0044 0044 0044 0044 0044 0044 02C7 09EE 09EF
        0AEE 0AEF 0AEE 0AEF 0AEE 0AEF 0AEE 0AEF 0AEE 0AEF 0AEE 0AEE 0AEF 02EB 0AEF 0AEE
        02EC 02ED 02EC 02ED 02EC 02ED 02EC 02ED 02EC 02ED 02EC 02EC 02ED 02C9 02ED 02EC
        02EE 02EF 02EE 02EF 02EE 02EF 02EE 02EF 02EE 02EF 02EE 02EE 02EF 02EA 02EF 02EE
        0AEE 0AEF 0AEE 0AEF 0AEE 0AEF 0AEE 0AEF 0AEE 0AEF 0AEE 0AEE 0AEF 02CA 0AEF 0AEE
        02EC 02ED 02EC 02ED 02EC 02ED 02EC 02ED 02EC 02ED 02EC 02EC 02ED 02E9 02ED 02EC
        02EE 02EF 02EE 02EF 02EE 02EF 02EE 02EF 02EE 02EF 02EE 02EE 02EF 02CB 02EF 02EE
        0044 0044 0044 0044 0044 0044 0044 0044 0044 0044 0044 0044 0044 02E8 0044 0044
        8983 8982 8D82 8D83 8983 8982 8D82 8D83 8983 8982 8983 8982 8983 8982 8983 8984
        8963 82C8 8D62 8D63 8963 8962 8D62 8D63 8963 82C8 8963 8962 8963 82C8 8965 8966
        8044 82E7 8044 8044 8044 8044 8044 8044 8044 82E7 8044 8044 8044 82E7 8165 8166
        8044 82C7 8044 8044 8044 8044 8044 8044 8044 82C7 8044 8044 8044 82C7 8185 8186
        8044 82E7 8044 8044 8044 8044 8044 8044 8044 82E7 8044 8044 8044 82E7 8167 8168
      </Screen>
          <Screen X="4" Y="0">
        8044 8044 8044 8044 8044 8044 8044 8044 8044 8044 8044 8044 8044 8044 8044 8044
        8163 8162 8163 8162 8562 8563 8562 8563 8163 8162 8562 8563 8163 8162 8562 8563
        8183 8182 8183 8182 8582 8583 8582 85A3 8183 8182 8582 8583 8183 8182 8582 8583
        0044 0044 0044 0044 0044 0044 0044 02C7 0044 0044 09EE 09EF 0044 0044 0044 0044
        0AEE 0AEF 0AEE 0AEF 0AEE 0AEE 0AEF 02EB 0AEF 0AEE 0AEE 0AEF 0AEE 0AEF 0AEE 0AEF
        02EC 02ED 02EC 02ED 02EC 02EC 02ED 02C9 02ED 02EC 02EC 02ED 02EC 02ED 02EC 02ED
        02EE 02EF 02EE 02EF 02EE 02EE 02EF 02EA 02EF 02EE 02EE 02EF 02EE 02EF 02EE 02EF
        0AEE 0AEF 0AEE 0AEF 0AEE 0AEE 0AEF 02CA 0AEF 0AEE 0AEE 0AEF 0AEE 0AEF 0AEE 0AEF
        02EC 02ED 02EC 02ED 02EC 02EC 02ED 02E9 02ED 02EC 02EC 02ED 02EC 02ED 02EC 02ED
        02EE 02EF 02EE 02EF 02EE 02EE 02EF 02CB 02EF 02EE 02EE 02EF 02EE 02EF 02EE 02EF
        0044 02E3 06E3 02C0 02E3 0044 0044 02E8 0044 0044 0044 0044 0044 0044 0044 01ED
        81FC 81FC 81FC 81FC 81FC 81FC 8983 8D83 8983 8982 8983 8982 8983 8984 81FC 81FC
        8129 8177 8176 8177 8176 8109 8D66 8D65 8963 8962 8963 8962 8965 8966 8176 82CB
        8109 8044 8044 8044 8044 8129 8566 8565 8044 8044 8044 8044 8165 8166 8044 82E7
        8109 8044 8044 8044 8044 8129 8586 8585 8044 8044 8044 8044 8185 8186 8044 82C7
        8109 8044 8044 8044 8044 8109 8568 8567 8044 8044 8044 8044 8167 8168 8044 82E7
      </Screen>
          <Screen X="5" Y="0">
        8044 8044 8044 8044 8044 8044 8044 8044 8187 8188 856F 816E 816F 0586 8585 8044
        8163 8162 8163 8162 8562 8563 8163 8162 8165 8166 856F 816E 816F 8566 8565 8163
        8183 8182 8183 8182 8582 8583 8183 8182 8183 8184 856F 816E 816F 8584 8583 8183
        0044 09EE 09EF 0044 0044 0044 0044 0044 0044 0044 8579 8178 8179 0044 0044 09EE
        0AEE 0AEF 0AEE 0AEF 0AEE 0AEF 0AEE 0AEF 0AEE 0AEF 0AEE 02EB 0AEE 0AEF 0AEE 0AEF
        02EC 02ED 02EC 02ED 02EC 02ED 02EC 02ED 02EC 02ED 02EC 02C9 02EC 02ED 02EC 02ED
        02EE 02EF 02EE 02EF 02EE 02EF 02EE 02EF 02EE 02EF 02EE 02EA 02EE 02EF 02EE 02EF
        0AEE 0AEF 0AEE 0AEF 0AEE 0AEF 0AEE 0AEF 0AEE 0AEF 0AEE 02CA 0AEE 0AEF 0AEE 0AEF
        02EC 02ED 02EC 02ED 02EC 02ED 02EC 02ED 02EC 02ED 02EC 02E9 02EC 02ED 02EC 02ED
        02EE 02EF 02EE 02EF 02EE 02EF 02EE 02EF 02EE 02EF 02EE 02CB 02EE 02EF 02EE 02EF
        0044 06E3 02E3 02E3 0044 0044 0044 0044 0044 0044 0044 02E8 0044 0044 0044 0044
        81FC 81FC 81FC 81FC 8D84 8D83 8983 8982 8983 8982 8983 8982 8983 8982 8983 8984
        81E9 81E9 82CB 8577 8D66 8D65 8963 8962 8963 8962 8963 82C8 8963 8962 8965 8966
        8044 8044 82E7 8444 8566 8565 8044 8044 8044 8044 8044 82E7 8044 8044 8165 8166
        8044 8044 82C7 8044 8586 8585 8044 8044 8044 8044 8044 82C7 8044 8044 8185 8186
        8044 8044 82E7 8044 8568 8567 8044 8044 8044 8044 8044 82E7 8044 8044 8167 8168
      </Screen>
          <Screen X="6" Y="0">
        8044 8044 8044 8044 8044 8044 8044 8044 8044 8044 8044 8044 8044 8044 8044 8044
        8162 8163 8162 8562 8563 8163 8162 8163 8162 8163 8162 8562 8563 8562 8563 8163
        8182 8183 8182 8582 8583 8183 8182 8183 8182 8183 85A3 8582 8583 8582 8583 8183
        09EF 0044 0044 0044 0044 0044 09EE 09EF 0044 0044 02C7 0044 0044 0044 0044 0044
        0AEE 0AEF 0AEE 0AEF 0AEE 0AEF 0AEE 0AEF 0AEE 0AEF 02EB 0AEF 0AEE 0AEF 0AEE 0AEF
        02EC 02ED 02EC 02ED 02EC 02ED 02EC 02ED 02EC 02ED 02C9 02ED 02EC 02ED 02EC 02ED
        02EE 02EF 02EE 02EF 02EE 02EF 02EE 02EF 02EE 02EF 02EA 02EF 02EE 02EF 02EE 02EF
        0AEE 0AEF 0AEE 0AEF 0AEE 0AEF 0AEE 0AEF 0AEE 0AEF 02CA 0AEF 0AEE 0AEF 0AEE 0AEF
        02EC 02ED 02EC 02ED 02EC 02ED 02EC 02ED 02EC 02ED 02E9 02ED 02EC 02ED 02EC 02ED
        02EE 02EF 02EE 02EF 02EE 02EF 02EE 02EF 02EE 02EF 02CB 02EF 02EE 02EF 02EE 02EF
        0044 01ED 0044 02C0 0044 0044 0044 0044 0044 0044 02E8 0044 0044 0044 0044 0044
        81FC 81FC 81FC 81FC 81FC 8D84 8D83 8D82 8D83 8983 8982 8983 8982 8D82 8D83 8983
        81E9 81FC 8116 81FC 81E9 8D66 8D65 8D62 8D63 8963 82C8 8963 8962 8D62 8D63 8963
        8176 81FC 81FC 81FC 8576 8566 8565 8044 8044 8044 82E7 8044 8044 8044 8044 8044
        8080 8044 8109 8044 8080 8586 8585 8044 8044 8044 82C7 8044 8044 8044 8044 8044
        8080 8044 8109 8044 8080 8568 8567 8044 8044 8044 82E7 8044 8044 8044 8044 8044
      </Screen>
          <Screen X="7" Y="0">
        8044 8044 8044 8187 8188 856F 816E 816F 856F 816E 816F 8586 8585 8044 8044 8044
        8162 8562 8563 8165 8166 856F 816E 816F 856F 816E 816F 8566 8565 8562 8561 8560
        8182 8582 85A3 8183 8184 856F 816E 816F 8579 8178 8179 8584 8583 8582 8581 8580
        0044 0044 02C7 0044 0044 8579 8178 8179 0044 81FC 81FC 09EE 09EF 0080 8566 8565
        0AEE 0AEF 02EB 0AEF 0AEE 0AEF 0AEE 0AEF 0AEE 81FC 81FC 0AEF 0AEE 0AEF 8586 8585
        02EC 02ED 02C9 02ED 02EC 02ED 02EC 02ED 02EC B116 B116 02ED 02EC 02ED 8568 8567
        02EE 02EF 02EA 02EF 02EE 02EF 02EE 02EF 02EE B116 02EE 02EF 02EE 02EF 8588 8587
        0AEE 0AEF 02CA 0AEF 0AEE 0AEF 0AEE 0AEF 0AEE B116 0AEE 0AEF 0AEE 0AEF 8568 8567
        02EC 02ED 02E9 02ED 02EC 02ED 02EC 02ED 02EC 02ED 02EC 02ED 816A 816B 816D 8587
        02EE 02EF 02CB 02EF 02EE 02EF 02EE 02EF 02EE 02EF 02EE 02EF 856F 896F 8566 8565
        0044 0044 02E8 0044 0044 0044 0044 0044 0044 0080 0080 0080 8D6F 816F 8584 8583
        8982 8983 8982 8D82 8D83 8983 8982 8983 8984 0080 0080 0080 8D6F 818E 816B 816B
        8962 8963 82C8 8D62 8D63 8963 8962 8965 8966 0080 0080 0080 856F 816E 8170 816E
        8044 8044 82E7 8044 8044 8044 8044 8165 8166 0080 0080 0080 856F 8970 816E 816E
        8044 8044 82C7 8044 8044 8044 8044 8185 8186 0080 0080 0080 856F 816E 816E 816E
        8044 8044 82E7 8044 8044 8044 8044 8167 8168 8109 8109 8109 8D6F 816E 816E 816E
      </Screen>
        </Layer1>
        <BTS>
          <Screen X="0" Y="0">
        00 00 00 00 00 00 00 00 00 00 00 00 00 00 00 00
        00 00 00 00 00 00 00 00 00 00 00 00 00 00 00 00
        00 00 00 00 00 00 00 00 00 00 00 00 00 00 00 00
        00 00 00 00 00 00 00 00 00 00 00 00 00 00 00 00
        00 00 00 00 00 00 00 00 00 00 00 00 00 00 04 04
        00 00 00 00 00 00 00 00 00 00 00 00 00 00 04 04
        00 00 00 00 00 00 00 00 00 00 00 00 00 00 00 00
        00 00 00 00 00 00 00 00 00 00 00 00 00 00 00 00
        00 00 00 00 00 00 00 00 00 00 00 00 00 00 00 00
        00 00 00 00 00 00 00 00 00 00 00 00 00 00 00 00
        00 00 00 00 00 00 42 FF FE FD 00 00 00 00 00 00
        00 00 00 00 00 00 00 00 00 00 00 00 00 00 00 00
        00 00 00 00 00 00 00 00 00 00 00 00 00 00 00 00
        00 00 00 00 00 00 00 00 00 00 00 00 00 00 00 00
        00 00 00 00 00 00 00 00 00 00 00 00 00 00 00 00
        00 00 00 00 00 00 00 00 00 00 00 00 00 00 00 00
      </Screen>
          <Screen X="1" Y="0">
        00 00 00 00 00 00 00 00 00 00 00 00 00 00 00 00
        00 00 00 00 00 00 00 00 00 00 00 00 00 00 00 00
        00 00 00 00 00 00 00 00 00 00 00 00 00 00 00 00
        00 00 00 00 00 00 00 00 00 00 00 00 00 00 00 00
        00 00 00 00 00 00 00 FF 00 00 00 00 00 00 00 00
        04 00 00 00 00 00 00 FE 00 00 00 00 00 00 00 00
        00 00 00 00 00 00 00 FD 00 00 00 00 00 00 00 00
        00 00 00 00 00 00 00 FC 00 00 00 00 00 00 00 00
        00 00 00 00 00 00 00 FB 00 00 00 00 00 00 00 00
        00 00 00 00 00 00 00 FA 00 00 00 00 00 00 00 00
        00 00 00 00 00 00 00 F9 00 00 00 00 00 00 00 00
        00 00 00 00 00 00 00 00 00 00 00 00 00 00 00 00
        00 00 00 00 00 00 00 00 00 00 00 00 00 00 00 00
        00 00 00 00 00 00 00 00 00 00 00 00 00 00 00 00
        00 00 00 00 00 00 00 00 00 00 00 00 00 00 00 00
        00 00 00 00 00 00 00 00 00 00 00 00 00 00 00 00
      </Screen>
          <Screen X="2" Y="0">
        00 00 00 00 00 00 00 00 00 00 00 00 00 00 00 00
        00 00 00 00 00 00 00 00 00 00 00 00 00 00 00 00
        00 00 00 00 00 00 00 00 00 00 00 00 00 00 00 00
        00 00 00 00 00 00 00 00 00 00 00 00 00 00 00 00
        00 00 00 00 00 00 00 00 00 00 00 00 00 00 00 00
        00 00 00 00 00 00 00 00 00 00 00 00 00 00 00 00
        00 00 00 00 00 00 00 00 00 00 00 00 00 00 00 00
        00 00 00 00 00 00 00 00 00 00 00 00 00 00 00 00
        00 00 00 00 00 00 00 00 00 00 00 00 00 00 00 00
        00 00 00 00 00 00 00 00 00 00 00 00 00 00 00 00
        00 00 00 00 00 00 00 00 00 00 00 00 00 00 00 00
        00 00 00 00 00 00 00 00 00 00 00 00 00 00 00 00
        00 00 00 00 00 00 00 00 00 00 00 00 00 00 00 00
        00 00 00 00 00 00 00 00 00 00 00 00 00 00 00 00
        00 00 00 00 00 00 00 00 00 00 00 00 00 00 00 00
        00 00 00 00 00 00 00 00 00 00 00 00 00 00 00 00
      </Screen>
          <Screen X="3" Y="0">
        00 00 00 00 00 00 01 01 01 01 00 00 00 00 00 00
        00 00 00 00 00 00 00 00 00 00 00 00 00 00 00 00
        00 00 00 00 00 00 43 FF FE FD 00 00 00 00 00 00
        00 00 00 00 00 00 00 00 00 00 00 00 00 00 00 00
        00 00 00 00 00 00 00 00 00 00 00 00 00 00 00 00
        00 00 00 00 00 00 00 00 00 00 00 00 00 00 00 00
        00 00 00 00 00 00 00 00 00 00 00 00 00 00 00 00
        00 00 00 00 00 00 00 00 00 00 00 00 00 00 00 00
        00 00 00 00 00 00 00 00 00 00 00 00 00 00 00 00
        00 00 00 00 00 00 00 00 00 00 00 00 00 00 00 00
        00 00 00 00 00 00 00 00 00 00 00 00 00 00 00 00
        00 00 00 00 00 00 00 00 00 00 00 00 00 00 00 00
        00 00 00 00 00 00 00 00 00 00 00 00 00 00 00 00
        00 00 00 00 00 00 00 00 00 00 00 00 00 00 00 00
        00 00 00 00 00 00 00 00 00 00 00 00 00 00 00 00
        00 00 00 00 00 00 00 00 00 00 00 00 00 00 00 00
      </Screen>
          <Screen X="4" Y="0">
        00 00 00 00 00 00 00 00 00 00 00 00 00 00 00 00
        00 00 00 00 00 00 00 00 00 00 00 00 00 00 00 00
        00 00 00 00 00 00 00 00 00 00 00 00 00 00 00 00
        00 00 00 00 00 00 00 00 00 00 00 00 00 00 00 00
        00 00 00 00 00 00 00 00 00 00 00 00 00 00 00 00
        00 00 00 00 00 00 00 00 00 00 00 00 00 00 00 00
        00 00 00 00 00 00 00 00 00 00 00 00 00 00 00 00
        00 00 00 00 00 00 00 00 00 00 00 00 00 00 00 00
        00 00 00 00 00 00 00 00 00 00 00 00 00 00 00 00
        00 00 00 00 00 00 00 00 00 00 00 00 00 00 00 00
        00 00 00 00 00 00 00 00 00 00 00 00 00 00 00 00
        00 00 00 00 00 00 00 00 00 00 00 00 00 00 00 00
        00 00 00 00 00 00 00 00 00 00 00 00 00 00 00 00
        00 00 00 00 00 00 00 00 00 00 00 00 00 00 00 00
        00 00 00 00 00 00 00 00 00 00 00 00 00 00 00 00
        00 00 00 00 00 00 00 00 00 00 00 00 00 00 00 00
      </Screen>
          <Screen X="5" Y="0">
        00 00 00 00 00 00 00 00 00 00 00 00 00 00 00 00
        00 00 00 00 00 00 00 00 00 00 00 00 00 00 00 00
        00 00 00 00 00 00 00 00 00 00 00 00 00 00 00 00
        00 00 00 00 00 00 00 00 00 00 00 00 00 00 00 00
        00 00 00 00 00 00 00 00 00 00 00 00 00 00 00 00
        00 00 00 00 00 00 00 00 00 00 00 00 00 00 00 00
        00 00 00 00 00 00 00 00 00 00 00 00 00 00 00 00
        00 00 00 00 00 00 00 00 00 00 00 00 00 00 00 00
        00 00 00 00 00 00 00 00 00 00 00 00 00 00 00 00
        00 00 00 00 00 00 00 00 00 00 00 00 00 00 00 00
        00 00 00 00 00 00 00 00 00 00 00 00 00 00 00 00
        00 00 00 00 00 00 00 00 00 00 00 00 00 00 00 00
        00 00 00 00 00 00 00 00 00 00 00 00 00 00 00 00
        00 00 00 00 00 00 00 00 00 00 00 00 00 00 00 00
        00 00 00 00 00 00 00 00 00 00 00 00 00 00 00 00
        00 00 00 00 00 00 00 00 00 00 00 00 00 00 00 00
      </Screen>
          <Screen X="6" Y="0">
        00 00 00 00 00 00 00 00 00 00 00 00 00 00 00 00
        00 00 00 00 00 00 00 00 00 00 00 00 00 00 00 00
        00 00 00 00 00 00 00 00 00 00 00 00 00 00 00 00
        00 00 00 00 00 00 00 00 00 00 00 00 00 00 00 00
        00 00 00 00 00 00 00 00 00 00 00 00 00 00 00 00
        00 00 00 00 00 00 00 00 00 00 00 00 00 00 00 00
        00 00 00 00 00 00 00 00 00 00 00 00 00 00 00 00
        00 00 00 00 00 00 00 00 00 00 00 00 00 00 00 00
        00 00 00 00 00 00 00 00 00 00 00 00 00 00 00 00
        00 00 00 00 00 00 00 00 00 00 00 00 00 00 00 00
        00 00 00 00 00 00 00 00 00 00 00 00 00 00 00 00
        00 00 00 00 00 00 00 00 00 00 00 00 00 00 00 00
        00 00 00 00 00 00 00 00 00 00 00 00 00 00 00 00
        00 00 00 00 00 00 00 00 00 00 00 00 00 00 00 00
        00 00 00 00 00 00 00 00 00 00 00 00 00 00 00 00
        00 00 00 00 00 00 00 00 00 00 00 00 00 00 00 00
      </Screen>
          <Screen X="7" Y="0">
        00 00 00 00 00 00 00 00 00 00 00 00 00 00 00 00
        00 00 00 00 00 00 00 00 00 00 00 00 00 00 00 00
        00 00 00 00 00 00 00 00 00 00 00 00 00 00 00 00
        00 00 00 00 00 00 00 00 00 00 00 00 00 00 00 00
        00 00 00 00 00 00 00 00 00 00 00 00 00 00 00 00
        00 00 00 00 00 00 00 00 00 0F 0F 00 00 00 00 00
        00 00 00 00 00 00 00 00 00 0F 00 00 00 00 00 00
        00 00 00 00 00 00 00 00 00 0F 00 00 00 00 00 00
        00 00 00 00 00 00 00 00 00 00 00 00 00 00 00 00
        00 00 00 00 00 00 00 00 00 00 00 00 00 00 00 00
        00 00 00 00 00 00 00 00 00 00 00 00 00 00 00 00
        00 00 00 00 00 00 00 00 00 00 00 00 00 00 00 00
        00 00 00 00 00 00 00 00 00 00 00 00 00 00 00 00
        00 00 00 00 00 00 00 00 00 00 00 00 00 00 00 00
        00 00 00 00 00 00 00 00 00 00 00 00 00 00 00 00
        00 00 00 00 00 00 00 00 00 00 00 00 00 00 00 00
      </Screen>
        </BTS>
      </LevelData>
      <GFXset>1B</GFXset>
      <music>0000</music>
      <FX1s>
        <FX1 default="true">
          <surfacestart>00C6</surfacestart>
          <surfacenew>FFFF</surfacenew>
          <surfacespeed>0000</surfacespeed>
          <surfacedelay>00</surfacedelay>
          <type>04</type>
          <transparency1_A>02</transparency1_A>
          <transparency2_B>02</transparency2_B>
          <liquidflags_C>81</liquidflags_C>
          <paletteflags>00</paletteflags>
          <animationflags>00</animationflags>
          <paletteblend>02</paletteblend>
        </FX1>
      </FX1s>
      <Enemies killcount="00">
        <Enemy>
          <ID>DDBF</ID>
          <X>0480</X>
          <Y>0078</Y>
          <tilemap>BD2A</tilemap>
          <special>2800</special>
          <gfx>0004</gfx>
          <speed>0000</speed>
          <speed2>0000</speed2>
        </Enemy>
        <Enemy>
          <ID>DDFF</ID>
          <X>0480</X>
          <Y>0078</Y>
          <tilemap>BD2A</tilemap>
          <special>A800</special>
          <gfx>0004</gfx>
          <speed>0000</speed>
          <speed2>0000</speed2>
        </Enemy>
      </Enemies>
      <EnemyTypes>
        <Enemy>
          <GFX>DDBF</GFX>
          <palette>D007</palette>
        </Enemy>
      </EnemyTypes>
      <layer2_type>BGData</layer2_type>
      <layer2_xscroll>00</layer2_xscroll>
      <layer2_yscroll>00</layer2_yscroll>
      <ScrollData>00 00 01 01 01 01 01 01 </ScrollData>
      <roomvar>0000</roomvar>
      <FX2>E8CD</FX2>
      <PLMs>
        <PLM>
          <type>C854</type>
          <x>36</x>
          <y>02</y>
          <arg>0069</arg>
        </PLM>
        <PLM>
          <type>EF47</type>
          <x>24</x>
          <y>0A</y>
          <arg>0056</arg>
        </PLM>
        <PLM>
          <type>FB00</type>
          <x>17</x>
          <y>03</y>
          <arg>A096</arg>
        </PLM>
        <PLM>
          <type>FB84</type>
          <x>00</x>
          <y>00</y>
          <arg>0000</arg>
        </PLM>
      </PLMs>
      <BGData>
        <Data Type="COPY">
          <SOURCE>7E2000</SOURCE>
          <DEST>4800</DEST>
          <SIZE>1000</SIZE>
        </Data>
      </BGData>
      <layer1_2>91F6</layer1_2>
    </State>
    <State condition="E629">
      <Arg>01</Arg>
      <LevelData Width="8" Height="1">
        <Layer1>
          <Screen X="0" Y="0">
        8044 8044 8044 8044 8044 8044 8044 8044 8044 8044 8044 8044 8044 8044 8044 8044
        8160 8161 8162 8562 8563 8163 8162 8163 8162 8562 8563 8562 8563 8163 8162 8163
        8180 8181 8182 8582 8583 8183 8182 8183 8182 8582 8583 8582 85A3 8183 8182 8183
        8165 8166 0044 0044 09EE 09EF 0080 0080 0080 09EE 09EF 0080 02C7 0080 0080 0080
        8185 8186 0044 0044 0044 0044 0044 0044 0044 0044 0044 0044 02E7 0044 F118 F118
        8167 8168 0AEE 0AEF 0AEE 0AEF 0AEE 0AEF 0AEE 0AEF 0AEE 0AEF 02E8 0044 F118 F118
        8187 8188 02EC 02ED 02EC 02ED 02EC 02ED 02EC 02ED 02EC 02ED 8D84 8D83 8D82 8D83
        8165 8166 02EC 02ED 02EC 02ED 02EC 02ED 02EC 02ED 02EC 02ED 8D66 8D65 8D62 8D63
        8167 8168 02EE 02EF 02EE 02EF 02EE 02EF 02EE 02EF 02EE 02EF 8566 8565 8044 8044
        8187 8981 8983 8984 0080 01ED 0044 0044 0044 0044 02C0 02E3 8586 8585 8044 8044
        8586 8585 8965 8966 81FC 81FC C41D 541C 501C 501D 81FC 81FC 8568 8567 8044 8044
        8568 8567 8165 8166 8109 8129 9443 9442 9042 9043 8109 8109 8588 8587 8044 8044
        8588 8587 8185 8186 8109 8129 8463 8462 8062 8063 8129 8129 8566 8565 8044 8044
        8566 8565 8167 8168 8129 8109 8463 8462 8062 8063 8129 8109 8586 8585 8044 8044
        8586 8585 8187 8188 8129 8109 8463 8462 8062 8063 8109 8109 8568 8567 8044 8044
        8568 8567 8165 8166 8109 8109 8463 8462 8062 8063 8109 8109 8588 8587 8044 8044
      </Screen>
          <Screen X="1" Y="0">
        8044 8044 8044 8044 8044 8044 8044 8044 8044 8044 8044 8044 8044 8187 8188 856F
        8162 8163 8162 8562 8563 8163 8162 8163 8162 8163 8162 8562 8563 8165 8166 856F
        8182 81A3 8182 8582 8583 8183 8182 8183 8182 81A3 8182 8582 8583 8183 8184 8579
        0080 02C7 0044 0044 0044 0044 0044 0044 0044 02C7 0044 09EE 09EF 0044 0044 0044
        0044 02E7 0044 0044 0044 0044 0044 D044 0044 02E7 0044 0044 0044 0044 0044 0044
        F118 02E8 0AEF 0AEE 0AEF 0AEE 0AEF DAEE 0AEF 030A 0044 0044 0044 0044 0044 0044
        8983 8984 02ED 02EC 02ED 02EC 02ED D2EC 02ED 0329 0044 0044 0044 0044 0044 0044
        8965 8966 02ED 02EC 02ED 02EC 02ED D2EC 02ED 0309 0044 0044 0044 0044 0044 0044
        8165 8166 02EF 02EE 02EF 02EE 02EF D2EE 02EF 032A 0044 0044 0044 0044 0044 0044
        8185 8186 0044 0044 0044 0044 0044 D044 0044 02C7 0044 0044 0044 0044 0044 0080
        8167 8168 0044 0044 0044 0044 0044 D044 0044 02E8 0044 0044 0044 0044 0080 0080
        8187 8188 0044 0044 8D84 8D83 8983 8982 8983 8982 8D82 8D83 8983 8982 8983 8984
        8165 8166 0044 0044 8D66 8D65 8963 8962 8963 82C8 8D62 8D63 8963 8962 8965 8966
        8185 8186 0044 0044 8566 8565 8044 8044 8044 82E7 8044 8044 8044 8044 8165 8166
        8167 8168 0080 0080 8586 8585 8044 8044 8044 82C7 8044 8044 8044 8044 8185 8186
        8187 8188 8109 8109 8568 8567 8044 8044 8044 82E7 8044 8044 8044 8044 8167 8168
      </Screen>
          <Screen X="2" Y="0">
        816E 816E 816E 816F 8588 8587 8044 8044 8044 8044 8044 8044 8044 8044 8044 8044
        816E 816E 816E 816F 8566 8565 8562 8563 8562 8563 8163 8162 8163 8162 8562 8563
        8178 8178 8178 8179 8584 8583 8582 8583 8582 85A3 8183 8182 8183 8182 8582 8583
        8165 8100 A101 0044 0080 09EE 09EF 0044 0080 02C7 0080 0044 09EE 09EF 0044 0044
        8185 8120 A121 0044 0044 0044 0044 0044 0044 034A 0AEF 0AEE 0AEE 0AEF 0AEE 0AEF
        8165 8100 A101 0044 0044 0044 0044 0044 0044 0349 02ED 02EC 02EC 02ED 02EC 02ED
        8185 8120 A121 0044 0044 0044 0044 0044 0044 036A 02EF 02EE 02EE 02EF 02EE 02EF
        8165 8100 A101 0044 0044 0044 0044 0044 0044 036B 0AEF 0AEE 0AEE 0AEF 0AEE 0AEF
        8185 8120 A121 0044 0044 0044 0044 0044 0044 0369 02ED 02EC 02EC 02ED 02EC 02ED
        8165 8100 A101 0044 0080 02C2 0080 0044 0080 034B 02EF 02EE 02EE 02EF 02EE 02EF
        8185 8120 A121 0044 0044 02E2 0044 0044 0044 02E7 0044 0044 0044 0080 0044 0044
        8171 816B 856B 856A 805D 8169 8D84 8D83 8983 8982 8983 8982 8D82 8D83 8983 8982
        856F 816E 816E 8170 8978 8189 8D66 8D65 8963 82C8 8963 8962 8D62 8D63 8963 8962
        856F 816E 8970 816E 816E 816F 8566 8565 8044 82E7 8044 8044 8044 8044 8044 8044
        856F 816E 816E 816E 816E 816F 8586 8585 8044 82C7 8044 8044 8044 8044 8044 8044
        856F 816E 816E 816E 816E 816F 8568 8567 8044 82E7 8044 8044 8044 8044 8044 8044
      </Screen>
          <Screen X="3" Y="0">
        8044 8044 8044 8044 8185 8186 9C63 9C62 9862 9863 8588 8587 8044 8044 8044 8044
        8163 8162 8562 8563 8165 8166 2C43 2C42 2842 2843 8566 8565 8562 8563 8562 8563
        8183 8182 8582 8583 8183 8184 CC1D 5C1C 581C 581D 8584 8583 8582 85A3 8582 8583
        0044 0044 0044 0044 0044 0044 0044 0044 0044 0044 0044 0044 0044 02C7 09EE 09EF
        0AEE 0AEF 0AEE 0AEF 0AEE 0AEF 0AEE 0AEF 0AEE 0AEF 0AEE 0AEE 0AEF 02EB 0AEF 0AEE
        02EC 02ED 02EC 02ED 02EC 02ED 02EC 02ED 02EC 02ED 02EC 02EC 02ED 02C9 02ED 02EC
        02EE 02EF 02EE 02EF 02EE 02EF 02EE 02EF 02EE 02EF 02EE 02EE 02EF 02EA 02EF 02EE
        0AEE 0AEF 0AEE 0AEF 0AEE 0AEF 0AEE 0AEF 0AEE 0AEF 0AEE 0AEE 0AEF 02CA 0AEF 0AEE
        02EC 02ED 02EC 02ED 02EC 02ED 02EC 02ED 02EC 02ED 02EC 02EC 02ED 02E9 02ED 02EC
        02EE 02EF 02EE 02EF 02EE 02EF 02EE 02EF 02EE 02EF 02EE 02EE 02EF 02CB 02EF 02EE
        0044 0044 0044 0044 0044 0044 0044 0044 0044 0044 0044 0044 0044 02E8 0044 0044
        8983 8982 8D82 8D83 8983 8982 8D82 8D83 8983 8982 8983 8982 8983 8982 8983 8984
        8963 82C8 8D62 8D63 8963 8962 8D62 8D63 8963 82C8 8963 8962 8963 82C8 8965 8966
        8044 82E7 8044 8044 8044 8044 8044 8044 8044 82E7 8044 8044 8044 82E7 8165 8166
        8044 82C7 8044 8044 8044 8044 8044 8044 8044 82C7 8044 8044 8044 82C7 8185 8186
        8044 82E7 8044 8044 8044 8044 8044 8044 8044 82E7 8044 8044 8044 82E7 8167 8168
      </Screen>
          <Screen X="4" Y="0">
        8044 8044 8044 8044 8044 8044 8044 8044 8044 8044 8044 8044 8044 8044 8044 8044
        8163 8162 8163 8162 8562 8563 8562 8563 8163 8162 8562 8563 8163 8162 8562 8563
        8183 8182 8183 8182 8582 8583 8582 85A3 8183 8182 8582 8583 8183 8182 8582 8583
        0044 0044 0044 0044 0044 0044 0044 02C7 0044 0044 09EE 09EF 0044 0044 0044 0044
        0AEE 0AEF 0AEE 0AEF 0AEE 0AEE 0AEF 02EB 0AEF 0AEE 0AEE 0AEF 0AEE 0AEF 0AEE 0AEF
        02EC 02ED 02EC 02ED 02EC 02EC 02ED 02C9 02ED 02EC 02EC 02ED 02EC 02ED 02EC 02ED
        02EE 02EF 02EE 02EF 02EE 02EE 02EF 02EA 02EF 02EE 02EE 02EF 02EE 02EF 02EE 02EF
        0AEE 0AEF 0AEE 0AEF 0AEE 0AEE 0AEF 02CA 0AEF 0AEE 0AEE 0AEF 0AEE 0AEF 0AEE 0AEF
        02EC 02ED 02EC 02ED 02EC 02EC 02ED 02E9 02ED 02EC 02EC 02ED 02EC 02ED 02EC 02ED
        02EE 02EF 02EE 02EF 02EE 02EE 02EF 02CB 02EF 02EE 02EE 02EF 02EE 02EF 02EE 02EF
        0044 02E3 06E3 02C0 02E3 0044 0044 02E8 0044 0044 0044 0044 0044 0044 0044 01ED
        81FC 81FC 81FC 81FC 81FC 81FC 8983 8D83 8983 8982 8983 8982 8983 8984 81FC 81FC
        8129 8177 8176 8177 8176 8109 8D66 8D65 8963 8962 8963 8962 8965 8966 8176 82CB
        8109 8044 8044 8044 8044 8129 8566 8565 8044 8044 8044 8044 8165 8166 8044 82E7
        8109 8044 8044 8044 8044 8129 8586 8585 8044 8044 8044 8044 8185 8186 8044 82C7
        8109 8044 8044 8044 8044 8109 8568 8567 8044 8044 8044 8044 8167 8168 8044 82E7
      </Screen>
          <Screen X="5" Y="0">
        8044 8044 8044 8044 8044 8044 8044 8044 8187 8188 856F 816E 816F 0586 8585 8044
        8163 8162 8163 8162 8562 8563 8163 8162 8165 8166 856F 816E 816F 8566 8565 8163
        8183 8182 8183 8182 8582 8583 8183 8182 8183 8184 856F 816E 816F 8584 8583 8183
        0044 09EE 09EF 0044 0044 0044 0044 0044 0044 0044 8579 8178 8179 0044 0044 09EE
        0AEE 0AEF 0AEE 0AEF 0AEE 0AEF 0AEE 0AEF 0AEE 0AEF 0AEE 02EB 0AEE 0AEF 0AEE 0AEF
        02EC 02ED 02EC 02ED 02EC 02ED 02EC 02ED 02EC 02ED 02EC 02C9 02EC 02ED 02EC 02ED
        02EE 02EF 02EE 02EF 02EE 02EF 02EE 02EF 02EE 02EF 02EE 02EA 02EE 02EF 02EE 02EF
        0AEE 0AEF 0AEE 0AEF 0AEE 0AEF 0AEE 0AEF 0AEE 0AEF 0AEE 02CA 0AEE 0AEF 0AEE 0AEF
        02EC 02ED 02EC 02ED 02EC 02ED 02EC 02ED 02EC 02ED 02EC 02E9 02EC 02ED 02EC 02ED
        02EE 02EF 02EE 02EF 02EE 02EF 02EE 02EF 02EE 02EF 02EE 02CB 02EE 02EF 02EE 02EF
        0044 06E3 02E3 02E3 0044 0044 0044 0044 0044 0044 0044 02E8 0044 0044 0044 0044
        81FC 81FC 81FC 81FC 8D84 8D83 8983 8982 8983 8982 8983 8982 8983 8982 8983 8984
        81E9 81E9 82CB 8577 8D66 8D65 8963 8962 8963 8962 8963 82C8 8963 8962 8965 8966
        8044 8044 82E7 8444 8566 8565 8044 8044 8044 8044 8044 82E7 8044 8044 8165 8166
        8044 8044 82C7 8044 8586 8585 8044 8044 8044 8044 8044 82C7 8044 8044 8185 8186
        8044 8044 82E7 8044 8568 8567 8044 8044 8044 8044 8044 82E7 8044 8044 8167 8168
      </Screen>
          <Screen X="6" Y="0">
        8044 8044 8044 8044 8044 8044 8044 8044 8044 8044 8044 8044 8044 8044 8044 8044
        8162 8163 8162 8562 8563 8163 8162 8163 8162 8163 8162 8562 8563 8562 8563 8163
        8182 8183 8182 8582 8583 8183 8182 8183 8182 8183 85A3 8582 8583 8582 8583 8183
        09EF 0044 0044 0044 0044 0044 09EE 09EF 0044 0044 02C7 0044 0044 0044 0044 0044
        0AEE 0AEF 0AEE 0AEF 0AEE 0AEF 0AEE 0AEF 0AEE 0AEF 02EB 0AEF 0AEE 0AEF 0AEE 0AEF
        02EC 02ED 02EC 02ED 02EC 02ED 02EC 02ED 02EC 02ED 02C9 02ED 02EC 02ED 02EC 02ED
        02EE 02EF 02EE 02EF 02EE 02EF 02EE 02EF 02EE 02EF 02EA 02EF 02EE 02EF 02EE 02EF
        0AEE 0AEF 0AEE 0AEF 0AEE 0AEF 0AEE 0AEF 0AEE 0AEF 02CA 0AEF 0AEE 0AEF 0AEE 0AEF
        02EC 02ED 02EC 02ED 02EC 02ED 02EC 02ED 02EC 02ED 02E9 02ED 02EC 02ED 02EC 02ED
        02EE 02EF 02EE 02EF 02EE 02EF 02EE 02EF 02EE 02EF 02CB 02EF 02EE 02EF 02EE 02EF
        0044 01ED 0044 02C0 0044 0044 0044 0044 0044 0044 02E8 0044 0044 0044 0044 0044
        81FC 81FC 81FC 81FC 81FC 8D84 8D83 8D82 8D83 8983 8982 8983 8982 8D82 8D83 8983
        81E9 81FC 8116 81FC 81E9 8D66 8D65 8D62 8D63 8963 82C8 8963 8962 8D62 8D63 8963
        8176 81FC 81FC 81FC 8576 8566 8565 8044 8044 8044 82E7 8044 8044 8044 8044 8044
        8080 8044 8109 8044 8080 8586 8585 8044 8044 8044 82C7 8044 8044 8044 8044 8044
        8080 8044 8109 8044 8080 8568 8567 8044 8044 8044 82E7 8044 8044 8044 8044 8044
      </Screen>
          <Screen X="7" Y="0">
        8044 8044 8044 8187 8188 856F 816E 816F 856F 816E 816F 8586 8585 8044 8044 8044
        8162 8562 8563 8165 8166 856F 816E 816F 856F 816E 816F 8566 8565 8562 8561 8560
        8182 8582 85A3 8183 8184 856F 816E 816F 8579 8178 8179 8584 8583 8582 8581 8580
        0044 0044 02C7 0044 0044 8579 8178 8179 0044 81FC 81FC 09EE 09EF 0080 8566 8565
        0AEE 0AEF 02EB 0AEF 0AEE 0AEF 0AEE 0AEF 0AEE 81FC 81FC 0AEF 0AEE 0AEF 8586 8585
        02EC 02ED 02C9 02ED 02EC 02ED 02EC 02ED 02EC B116 B116 02ED 02EC 02ED 8568 8567
        02EE 02EF 02EA 02EF 02EE 02EF 02EE 02EF 02EE B116 02EE 02EF 02EE 02EF 8588 8587
        0AEE 0AEF 02CA 0AEF 0AEE 0AEF 0AEE 0AEF 0AEE B116 0AEE 0AEF 0AEE 0AEF 8568 8567
        02EC 02ED 02E9 02ED 02EC 02ED 02EC 02ED 02EC 02ED 02EC 02ED 816A 816B 816D 8587
        02EE 02EF 02CB 02EF 02EE 02EF 02EE 02EF 02EE 02EF 02EE 02EF 856F 896F 8566 8565
        0044 0044 02E8 0044 0044 0044 0044 0044 0044 0080 0080 0080 8D6F 816F 8584 8583
        8982 8983 8982 8D82 8D83 8983 8982 8983 8984 0080 0080 0080 8D6F 818E 816B 816B
        8962 8963 82C8 8D62 8D63 8963 8962 8965 8966 0080 0080 0080 856F 816E 8170 816E
        8044 8044 82E7 8044 8044 8044 8044 8165 8166 0080 0080 0080 856F 8970 816E 816E
        8044 8044 82C7 8044 8044 8044 8044 8185 8186 0080 0080 0080 856F 816E 816E 816E
        8044 8044 82E7 8044 8044 8044 8044 8167 8168 8109 8109 8109 8D6F 816E 816E 816E
      </Screen>
        </Layer1>
        <BTS>
          <Screen X="0" Y="0">
        00 00 00 00 00 00 00 00 00 00 00 00 00 00 00 00
        00 00 00 00 00 00 00 00 00 00 00 00 00 00 00 00
        00 00 00 00 00 00 00 00 00 00 00 00 00 00 00 00
        00 00 00 00 00 00 00 00 00 00 00 00 00 00 00 00
        00 00 00 00 00 00 00 00 00 00 00 00 00 00 04 04
        00 00 00 00 00 00 00 00 00 00 00 00 00 00 04 04
        00 00 00 00 00 00 00 00 00 00 00 00 00 00 00 00
        00 00 00 00 00 00 00 00 00 00 00 00 00 00 00 00
        00 00 00 00 00 00 00 00 00 00 00 00 00 00 00 00
        00 00 00 00 00 00 00 00 00 00 00 00 00 00 00 00
        00 00 00 00 00 00 42 FF FE FD 00 00 00 00 00 00
        00 00 00 00 00 00 00 00 00 00 00 00 00 00 00 00
        00 00 00 00 00 00 00 00 00 00 00 00 00 00 00 00
        00 00 00 00 00 00 00 00 00 00 00 00 00 00 00 00
        00 00 00 00 00 00 00 00 00 00 00 00 00 00 00 00
        00 00 00 00 00 00 00 00 00 00 00 00 00 00 00 00
      </Screen>
          <Screen X="1" Y="0">
        00 00 00 00 00 00 00 00 00 00 00 00 00 00 00 00
        00 00 00 00 00 00 00 00 00 00 00 00 00 00 00 00
        00 00 00 00 00 00 00 00 00 00 00 00 00 00 00 00
        00 00 00 00 00 00 00 00 00 00 00 00 00 00 00 00
        00 00 00 00 00 00 00 FF 00 00 00 00 00 00 00 00
        04 00 00 00 00 00 00 FE 00 00 00 00 00 00 00 00
        00 00 00 00 00 00 00 FD 00 00 00 00 00 00 00 00
        00 00 00 00 00 00 00 FC 00 00 00 00 00 00 00 00
        00 00 00 00 00 00 00 FB 00 00 00 00 00 00 00 00
        00 00 00 00 00 00 00 FA 00 00 00 00 00 00 00 00
        00 00 00 00 00 00 00 F9 00 00 00 00 00 00 00 00
        00 00 00 00 00 00 00 00 00 00 00 00 00 00 00 00
        00 00 00 00 00 00 00 00 00 00 00 00 00 00 00 00
        00 00 00 00 00 00 00 00 00 00 00 00 00 00 00 00
        00 00 00 00 00 00 00 00 00 00 00 00 00 00 00 00
        00 00 00 00 00 00 00 00 00 00 00 00 00 00 00 00
      </Screen>
          <Screen X="2" Y="0">
        00 00 00 00 00 00 00 00 00 00 00 00 00 00 00 00
        00 00 00 00 00 00 00 00 00 00 00 00 00 00 00 00
        00 00 00 00 00 00 00 00 00 00 00 00 00 00 00 00
        00 00 00 00 00 00 00 00 00 00 00 00 00 00 00 00
        00 00 00 00 00 00 00 00 00 00 00 00 00 00 00 00
        00 00 00 00 00 00 00 00 00 00 00 00 00 00 00 00
        00 00 00 00 00 00 00 00 00 00 00 00 00 00 00 00
        00 00 00 00 00 00 00 00 00 00 00 00 00 00 00 00
        00 00 00 00 00 00 00 00 00 00 00 00 00 00 00 00
        00 00 00 00 00 00 00 00 00 00 00 00 00 00 00 00
        00 00 00 00 00 00 00 00 00 00 00 00 00 00 00 00
        00 00 00 00 00 00 00 00 00 00 00 00 00 00 00 00
        00 00 00 00 00 00 00 00 00 00 00 00 00 00 00 00
        00 00 00 00 00 00 00 00 00 00 00 00 00 00 00 00
        00 00 00 00 00 00 00 00 00 00 00 00 00 00 00 00
        00 00 00 00 00 00 00 00 00 00 00 00 00 00 00 00
      </Screen>
          <Screen X="3" Y="0">
        00 00 00 00 00 00 01 01 01 01 00 00 00 00 00 00
        00 00 00 00 00 00 00 00 00 00 00 00 00 00 00 00
        00 00 00 00 00 00 43 FF FE FD 00 00 00 00 00 00
        00 00 00 00 00 00 00 00 00 00 00 00 00 00 00 00
        00 00 00 00 00 00 00 00 00 00 00 00 00 00 00 00
        00 00 00 00 00 00 00 00 00 00 00 00 00 00 00 00
        00 00 00 00 00 00 00 00 00 00 00 00 00 00 00 00
        00 00 00 00 00 00 00 00 00 00 00 00 00 00 00 00
        00 00 00 00 00 00 00 00 00 00 00 00 00 00 00 00
        00 00 00 00 00 00 00 00 00 00 00 00 00 00 00 00
        00 00 00 00 00 00 00 00 00 00 00 00 00 00 00 00
        00 00 00 00 00 00 00 00 00 00 00 00 00 00 00 00
        00 00 00 00 00 00 00 00 00 00 00 00 00 00 00 00
        00 00 00 00 00 00 00 00 00 00 00 00 00 00 00 00
        00 00 00 00 00 00 00 00 00 00 00 00 00 00 00 00
        00 00 00 00 00 00 00 00 00 00 00 00 00 00 00 00
      </Screen>
          <Screen X="4" Y="0">
        00 00 00 00 00 00 00 00 00 00 00 00 00 00 00 00
        00 00 00 00 00 00 00 00 00 00 00 00 00 00 00 00
        00 00 00 00 00 00 00 00 00 00 00 00 00 00 00 00
        00 00 00 00 00 00 00 00 00 00 00 00 00 00 00 00
        00 00 00 00 00 00 00 00 00 00 00 00 00 00 00 00
        00 00 00 00 00 00 00 00 00 00 00 00 00 00 00 00
        00 00 00 00 00 00 00 00 00 00 00 00 00 00 00 00
        00 00 00 00 00 00 00 00 00 00 00 00 00 00 00 00
        00 00 00 00 00 00 00 00 00 00 00 00 00 00 00 00
        00 00 00 00 00 00 00 00 00 00 00 00 00 00 00 00
        00 00 00 00 00 00 00 00 00 00 00 00 00 00 00 00
        00 00 00 00 00 00 00 00 00 00 00 00 00 00 00 00
        00 00 00 00 00 00 00 00 00 00 00 00 00 00 00 00
        00 00 00 00 00 00 00 00 00 00 00 00 00 00 00 00
        00 00 00 00 00 00 00 00 00 00 00 00 00 00 00 00
        00 00 00 00 00 00 00 00 00 00 00 00 00 00 00 00
      </Screen>
          <Screen X="5" Y="0">
        00 00 00 00 00 00 00 00 00 00 00 00 00 00 00 00
        00 00 00 00 00 00 00 00 00 00 00 00 00 00 00 00
        00 00 00 00 00 00 00 00 00 00 00 00 00 00 00 00
        00 00 00 00 00 00 00 00 00 00 00 00 00 00 00 00
        00 00 00 00 00 00 00 00 00 00 00 00 00 00 00 00
        00 00 00 00 00 00 00 00 00 00 00 00 00 00 00 00
        00 00 00 00 00 00 00 00 00 00 00 00 00 00 00 00
        00 00 00 00 00 00 00 00 00 00 00 00 00 00 00 00
        00 00 00 00 00 00 00 00 00 00 00 00 00 00 00 00
        00 00 00 00 00 00 00 00 00 00 00 00 00 00 00 00
        00 00 00 00 00 00 00 00 00 00 00 00 00 00 00 00
        00 00 00 00 00 00 00 00 00 00 00 00 00 00 00 00
        00 00 00 00 00 00 00 00 00 00 00 00 00 00 00 00
        00 00 00 00 00 00 00 00 00 00 00 00 00 00 00 00
        00 00 00 00 00 00 00 00 00 00 00 00 00 00 00 00
        00 00 00 00 00 00 00 00 00 00 00 00 00 00 00 00
      </Screen>
          <Screen X="6" Y="0">
        00 00 00 00 00 00 00 00 00 00 00 00 00 00 00 00
        00 00 00 00 00 00 00 00 00 00 00 00 00 00 00 00
        00 00 00 00 00 00 00 00 00 00 00 00 00 00 00 00
        00 00 00 00 00 00 00 00 00 00 00 00 00 00 00 00
        00 00 00 00 00 00 00 00 00 00 00 00 00 00 00 00
        00 00 00 00 00 00 00 00 00 00 00 00 00 00 00 00
        00 00 00 00 00 00 00 00 00 00 00 00 00 00 00 00
        00 00 00 00 00 00 00 00 00 00 00 00 00 00 00 00
        00 00 00 00 00 00 00 00 00 00 00 00 00 00 00 00
        00 00 00 00 00 00 00 00 00 00 00 00 00 00 00 00
        00 00 00 00 00 00 00 00 00 00 00 00 00 00 00 00
        00 00 00 00 00 00 00 00 00 00 00 00 00 00 00 00
        00 00 00 00 00 00 00 00 00 00 00 00 00 00 00 00
        00 00 00 00 00 00 00 00 00 00 00 00 00 00 00 00
        00 00 00 00 00 00 00 00 00 00 00 00 00 00 00 00
        00 00 00 00 00 00 00 00 00 00 00 00 00 00 00 00
      </Screen>
          <Screen X="7" Y="0">
        00 00 00 00 00 00 00 00 00 00 00 00 00 00 00 00
        00 00 00 00 00 00 00 00 00 00 00 00 00 00 00 00
        00 00 00 00 00 00 00 00 00 00 00 00 00 00 00 00
        00 00 00 00 00 00 00 00 00 00 00 00 00 00 00 00
        00 00 00 00 00 00 00 00 00 00 00 00 00 00 00 00
        00 00 00 00 00 00 00 00 00 0F 0F 00 00 00 00 00
        00 00 00 00 00 00 00 00 00 0F 00 00 00 00 00 00
        00 00 00 00 00 00 00 00 00 0F 00 00 00 00 00 00
        00 00 00 00 00 00 00 00 00 00 00 00 00 00 00 00
        00 00 00 00 00 00 00 00 00 00 00 00 00 00 00 00
        00 00 00 00 00 00 00 00 00 00 00 00 00 00 00 00
        00 00 00 00 00 00 00 00 00 00 00 00 00 00 00 00
        00 00 00 00 00 00 00 00 00 00 00 00 00 00 00 00
        00 00 00 00 00 00 00 00 00 00 00 00 00 00 00 00
        00 00 00 00 00 00 00 00 00 00 00 00 00 00 00 00
        00 00 00 00 00 00 00 00 00 00 00 00 00 00 00 00
      </Screen>
        </BTS>
      </LevelData>
      <GFXset>1B</GFXset>
      <music>0000</music>
      <FX1s>
        <FX1 default="true">
          <surfacestart>00C6</surfacestart>
          <surfacenew>FFFF</surfacenew>
          <surfacespeed>0000</surfacespeed>
          <surfacedelay>00</surfacedelay>
          <type>04</type>
          <transparency1_A>02</transparency1_A>
          <transparency2_B>02</transparency2_B>
          <liquidflags_C>81</liquidflags_C>
          <paletteflags>00</paletteflags>
          <animationflags>00</animationflags>
          <paletteblend>02</paletteblend>
        </FX1>
      </FX1s>
      <Enemies killcount="00">
        <Enemy>
          <ID>DDBF</ID>
          <X>0480</X>
          <Y>0078</Y>
          <tilemap>BD2A</tilemap>
          <special>2800</special>
          <gfx>0004</gfx>
          <speed>0000</speed>
          <speed2>0000</speed2>
        </Enemy>
        <Enemy>
          <ID>DDFF</ID>
          <X>0480</X>
          <Y>0078</Y>
          <tilemap>BD2A</tilemap>
          <special>A800</special>
          <gfx>0004</gfx>
          <speed>0000</speed>
          <speed2>0000</speed2>
        </Enemy>
      </Enemies>
      <EnemyTypes>
        <Enemy>
          <GFX>DDBF</GFX>
          <palette>D007</palette>
        </Enemy>
      </EnemyTypes>
      <layer2_type>BGData</layer2_type>
      <layer2_xscroll>00</layer2_xscroll>
      <layer2_yscroll>00</layer2_yscroll>
      <ScrollData>00 00 01 01 01 01 01 01 </ScrollData>
      <roomvar>0000</roomvar>
      <FX2>E8CD</FX2>
      <PLMs>
        <PLM>
          <type>C854</type>
          <x>36</x>
          <y>02</y>
          <arg>0069</arg>
        </PLM>
        <PLM>
          <type>EF4B</type>
          <x>24</x>
          <y>0A</y>
          <arg>0056</arg>
        </PLM>
        <PLM>
          <type>FB00</type>
          <x>17</x>
          <y>03</y>
          <arg>A096</arg>
        </PLM>
        <PLM>
          <type>FB84</type>
          <x>00</x>
          <y>00</y>
          <arg>0000</arg>
        </PLM>
      </PLMs>
      <BGData>
        <Data Type="COPY">
          <SOURCE>7E2000</SOURCE>
          <DEST>4800</DEST>
          <SIZE>1000</SIZE>
        </Data>
      </BGData>
      <layer1_2>91F6</layer1_2>
    </State>
    <State condition="E612">
      <Arg>39</Arg>
      <LevelData Width="8" Height="1">
        <Layer1>
          <Screen X="0" Y="0">
        8044 8044 8044 8044 8044 8044 8044 8044 8044 8044 8044 8044 8044 8044 8044 8044
        8160 8161 8162 8562 8563 8163 8162 8163 8162 8562 8563 8562 8563 8163 8162 8163
        8180 8181 8182 8582 8583 8183 8182 8183 8182 8582 8583 8582 85A3 8183 8182 8183
        8165 8166 0044 0044 09EE 09EF 0080 0080 0080 09EE 09EF 0080 02C7 0080 0080 0080
        8185 8186 0044 0044 0044 0044 0044 0044 0044 0044 0044 0044 02E7 0044 F118 F118
        8167 8168 0AEE 0AEF 0AEE 0AEF 0AEE 0AEF 0AEE 0AEF 0AEE 0AEF 02E8 0044 F118 F118
        8187 8188 02EC 02ED 02EC 02ED 02EC 02ED 02EC 02ED 02EC 02ED 8D84 8D83 8D82 8D83
        8165 8166 02EC 02ED 02EC 02ED 02EC 02ED 02EC 02ED 02EC 02ED 8D66 8D65 8D62 8D63
        8167 8168 02EE 02EF 02EE 02EF 02EE 02EF 02EE 02EF 02EE 02EF 8566 8565 8044 8044
        8187 8981 8983 8984 0080 01ED 0044 0044 0044 0044 02C0 02E3 8586 8585 8044 8044
        8586 8585 8965 8966 81FC 81FC C41D 541C 501C 501D 81FC 81FC 8568 8567 8044 8044
        8568 8567 8165 8166 8109 8129 9443 9442 9042 9043 8109 8109 8588 8587 8044 8044
        8588 8587 8185 8186 8109 8129 8463 8462 8062 8063 8129 8129 8566 8565 8044 8044
        8566 8565 8167 8168 8129 8109 8463 8462 8062 8063 8129 8109 8586 8585 8044 8044
        8586 8585 8187 8188 8129 8109 8463 8462 8062 8063 8109 8109 8568 8567 8044 8044
        8568 8567 8165 8166 8109 8109 8463 8462 8062 8063 8109 8109 8588 8587 8044 8044
      </Screen>
          <Screen X="1" Y="0">
        8044 8044 8044 8044 8044 8044 8044 8044 8044 8044 8044 8044 8044 8187 8188 856F
        8162 8163 8162 8562 8563 8163 8162 8163 8162 8163 8162 8562 8563 8165 8166 856F
        8182 81A3 8182 8582 8583 8183 8182 8183 8182 81A3 8182 8582 8583 8183 8184 8579
        0080 02C7 0044 0044 0044 0044 0044 0044 0044 02C7 0044 09EE 09EF 0044 0044 0044
        0044 02E7 0044 0044 0044 0044 0044 D044 0044 02E7 0044 0044 0044 0044 0044 0044
        F118 02E8 0AEF 0AEE 0AEF 0AEE 0AEF DAEE 0AEF 030A 0044 0044 0044 0044 0044 0044
        8983 8984 02ED 02EC 02ED 02EC 02ED D2EC 02ED 0329 0044 0044 0044 0044 0044 0044
        8965 8966 02ED 02EC 02ED 02EC 02ED D2EC 02ED 0309 0044 0044 0044 0044 0044 0044
        8165 8166 02EF 02EE 02EF 02EE 02EF D2EE 02EF 032A 0044 0044 0044 0044 0044 0044
        8185 8186 0044 0044 0044 0044 0044 D044 0044 02C7 0044 0044 0044 0044 0044 0080
        8167 8168 0044 0044 0044 0044 0044 D044 0044 02E8 0044 0044 0044 0044 0080 0080
        8187 8188 0044 0044 8D84 8D83 8983 8982 8983 8982 8D82 8D83 8983 8982 8983 8984
        8165 8166 0044 0044 8D66 8D65 8963 8962 8963 82C8 8D62 8D63 8963 8962 8965 8966
        8185 8186 0044 0044 8566 8565 8044 8044 8044 82E7 8044 8044 8044 8044 8165 8166
        8167 8168 0080 0080 8586 8585 8044 8044 8044 82C7 8044 8044 8044 8044 8185 8186
        8187 8188 8109 8109 8568 8567 8044 8044 8044 82E7 8044 8044 8044 8044 8167 8168
      </Screen>
          <Screen X="2" Y="0">
        816E 816E 816E 816F 8588 8587 8044 8044 8044 8044 8044 8044 8044 8044 8044 8044
        816E 816E 816E 816F 8566 8565 8562 8563 8562 8563 8163 8162 8163 8162 8562 8563
        8178 8178 8178 8179 8584 8583 8582 8583 8582 85A3 8183 8182 8183 8182 8582 8583
        8165 8100 A101 0044 0080 09EE 09EF 0044 0080 02C7 0080 0044 09EE 09EF 0044 0044
        8185 8120 A121 0044 0044 0044 0044 0044 0044 034A 0AEF 0AEE 0AEE 0AEF 0AEE 0AEF
        8165 8100 A101 0044 0044 0044 0044 0044 0044 0349 02ED 02EC 02EC 02ED 02EC 02ED
        8185 8120 A121 0044 0044 0044 0044 0044 0044 036A 02EF 02EE 02EE 02EF 02EE 02EF
        8165 8100 A101 0044 0044 0044 0044 0044 0044 036B 0AEF 0AEE 0AEE 0AEF 0AEE 0AEF
        8185 8120 A121 0044 0044 0044 0044 0044 0044 0369 02ED 02EC 02EC 02ED 02EC 02ED
        8165 8100 A101 0044 0080 02C2 0080 0044 0080 034B 02EF 02EE 02EE 02EF 02EE 02EF
        8185 8120 A121 0044 0044 02E2 0044 0044 0044 02E7 0044 0044 0044 0080 0044 0044
        8171 816B 856B 856A 805D 8169 8D84 8D83 8983 8982 8983 8982 8D82 8D83 8983 8982
        856F 816E 816E 8170 8978 8189 8D66 8D65 8963 82C8 8963 8962 8D62 8D63 8963 8962
        856F 816E 8970 816E 816E 816F 8566 8565 8044 82E7 8044 8044 8044 8044 8044 8044
        856F 816E 816E 816E 816E 816F 8586 8585 8044 82C7 8044 8044 8044 8044 8044 8044
        856F 816E 816E 816E 816E 816F 8568 8567 8044 82E7 8044 8044 8044 8044 8044 8044
      </Screen>
          <Screen X="3" Y="0">
        8044 8044 8044 8044 8185 8186 9C63 9C62 9862 9863 8588 8587 8044 8044 8044 8044
        8163 8162 8562 8563 8165 8166 2C43 2C42 2842 2843 8566 8565 8562 8563 8562 8563
        8183 8182 8582 8583 8183 8184 CC1D 5C1C 581C 581D 8584 8583 8582 85A3 8582 8583
        0044 0044 0044 0044 0044 0044 0044 0044 0044 0044 0044 0044 0044 02C7 09EE 09EF
        0AEE 0AEF 0AEE 0AEF 0AEE 0AEF 0AEE 0AEF 0AEE 0AEF 0AEE 0AEE 0AEF 02EB 0AEF 0AEE
        02EC 02ED 02EC 02ED 02EC 02ED 02EC 02ED 02EC 02ED 02EC 02EC 02ED 02C9 02ED 02EC
        02EE 02EF 02EE 02EF 02EE 02EF 02EE 02EF 02EE 02EF 02EE 02EE 02EF 02EA 02EF 02EE
        0AEE 0AEF 0AEE 0AEF 0AEE 0AEF 0AEE 0AEF 0AEE 0AEF 0AEE 0AEE 0AEF 02CA 0AEF 0AEE
        02EC 02ED 02EC 02ED 02EC 02ED 02EC 02ED 02EC 02ED 02EC 02EC 02ED 02E9 02ED 02EC
        02EE 02EF 02EE 02EF 02EE 02EF 02EE 02EF 02EE 02EF 02EE 02EE 02EF 02CB 02EF 02EE
        0044 0044 0044 0044 0044 0044 0044 0044 0044 0044 0044 0044 0044 02E8 0044 0044
        8983 8982 8D82 8D83 8983 8982 8D82 8D83 8983 8982 8983 8982 8983 8982 8983 8984
        8963 82C8 8D62 8D63 8963 8962 8D62 8D63 8963 82C8 8963 8962 8963 82C8 8965 8966
        8044 82E7 8044 8044 8044 8044 8044 8044 8044 82E7 8044 8044 8044 82E7 8165 8166
        8044 82C7 8044 8044 8044 8044 8044 8044 8044 82C7 8044 8044 8044 82C7 8185 8186
        8044 82E7 8044 8044 8044 8044 8044 8044 8044 82E7 8044 8044 8044 82E7 8167 8168
      </Screen>
          <Screen X="4" Y="0">
        8044 8044 8044 8044 8044 8044 8044 8044 8044 8044 8044 8044 8044 8044 8044 8044
        8163 8162 8163 8162 8562 8563 8562 8563 8163 8162 8562 8563 8163 8162 8562 8563
        8183 8182 8183 8182 8582 8583 8582 85A3 8183 8182 8582 8583 8183 8182 8582 8583
        0044 0044 0044 0044 0044 0044 0044 02C7 0044 0044 09EE 09EF 0044 0044 0044 0044
        0AEE 0AEF 0AEE 0AEF 0AEE 0AEE 0AEF 02EB 0AEF 0AEE 0AEE 0AEF 0AEE 0AEF 0AEE 0AEF
        02EC 02ED 02EC 02ED 02EC 02EC 02ED 02C9 02ED 02EC 02EC 02ED 02EC 02ED 02EC 02ED
        02EE 02EF 02EE 02EF 02EE 02EE 02EF 02EA 02EF 02EE 02EE 02EF 02EE 02EF 02EE 02EF
        0AEE 0AEF 0AEE 0AEF 0AEE 0AEE 0AEF 02CA 0AEF 0AEE 0AEE 0AEF 0AEE 0AEF 0AEE 0AEF
        02EC 02ED 02EC 02ED 02EC 02EC 02ED 02E9 02ED 02EC 02EC 02ED 02EC 02ED 02EC 02ED
        02EE 02EF 02EE 02EF 02EE 02EE 02EF 02CB 02EF 02EE 02EE 02EF 02EE 02EF 02EE 02EF
        0044 02E3 06E3 02C0 02E3 0044 0044 02E8 0044 0044 0044 0044 0044 0044 0044 01ED
        81FC 81FC 81FC 81FC 81FC 81FC 8983 8D83 8983 8982 8983 8982 8983 8984 81FC 81FC
        8129 8177 8176 8177 8176 8109 8D66 8D65 8963 8962 8963 8962 8965 8966 8176 82CB
        8109 8044 8044 8044 8044 8129 8566 8565 8044 8044 8044 8044 8165 8166 8044 82E7
        8109 8044 8044 8044 8044 8129 8586 8585 8044 8044 8044 8044 8185 8186 8044 82C7
        8109 8044 8044 8044 8044 8109 8568 8567 8044 8044 8044 8044 8167 8168 8044 82E7
      </Screen>
          <Screen X="5" Y="0">
        8044 8044 8044 8044 8044 8044 8044 8044 8187 8188 856F 816E 816F 0586 8585 8044
        8163 8162 8163 8162 8562 8563 8163 8162 8165 8166 856F 816E 816F 8566 8565 8163
        8183 8182 8183 8182 8582 8583 8183 8182 8183 8184 856F 816E 816F 8584 8583 8183
        0044 09EE 09EF 0044 0044 0044 0044 0044 0044 0044 8579 8178 8179 0044 0044 09EE
        0AEE 0AEF 0AEE 0AEF 0AEE 0AEF 0AEE 0AEF 0AEE 0AEF 0AEE 02EB 0AEE 0AEF 0AEE 0AEF
        02EC 02ED 02EC 02ED 02EC 02ED 02EC 02ED 02EC 02ED 02EC 02C9 02EC 02ED 02EC 02ED
        02EE 02EF 02EE 02EF 02EE 02EF 02EE 02EF 02EE 02EF 02EE 02EA 02EE 02EF 02EE 02EF
        0AEE 0AEF 0AEE 0AEF 0AEE 0AEF 0AEE 0AEF 0AEE 0AEF 0AEE 02CA 0AEE 0AEF 0AEE 0AEF
        02EC 02ED 02EC 02ED 02EC 02ED 02EC 02ED 02EC 02ED 02EC 02E9 02EC 02ED 02EC 02ED
        02EE 02EF 02EE 02EF 02EE 02EF 02EE 02EF 02EE 02EF 02EE 02CB 02EE 02EF 02EE 02EF
        0044 06E3 02E3 02E3 0044 0044 0044 0044 0044 0044 0044 02E8 0044 0044 0044 0044
        81FC 81FC 81FC 81FC 8D84 8D83 8983 8982 8983 8982 8983 8982 8983 8982 8983 8984
        81E9 81E9 82CB 8577 8D66 8D65 8963 8962 8963 8962 8963 82C8 8963 8962 8965 8966
        8044 8044 82E7 8444 8566 8565 8044 8044 8044 8044 8044 82E7 8044 8044 8165 8166
        8044 8044 82C7 8044 8586 8585 8044 8044 8044 8044 8044 82C7 8044 8044 8185 8186
        8044 8044 82E7 8044 8568 8567 8044 8044 8044 8044 8044 82E7 8044 8044 8167 8168
      </Screen>
          <Screen X="6" Y="0">
        8044 8044 8044 8044 8044 8044 8044 8044 8044 8044 8044 8044 8044 8044 8044 8044
        8162 8163 8162 8562 8563 8163 8162 8163 8162 8163 8162 8562 8563 8562 8563 8163
        8182 8183 8182 8582 8583 8183 8182 8183 8182 8183 85A3 8582 8583 8582 8583 8183
        09EF 0044 0044 0044 0044 0044 09EE 09EF 0044 0044 02C7 0044 0044 0044 0044 0044
        0AEE 0AEF 0AEE 0AEF 0AEE 0AEF 0AEE 0AEF 0AEE 0AEF 02EB 0AEF 0AEE 0AEF 0AEE 0AEF
        02EC 02ED 02EC 02ED 02EC 02ED 02EC 02ED 02EC 02ED 02C9 02ED 02EC 02ED 02EC 02ED
        02EE 02EF 02EE 02EF 02EE 02EF 02EE 02EF 02EE 02EF 02EA 02EF 02EE 02EF 02EE 02EF
        0AEE 0AEF 0AEE 0AEF 0AEE 0AEF 0AEE 0AEF 0AEE 0AEF 02CA 0AEF 0AEE 0AEF 0AEE 0AEF
        02EC 02ED 02EC 02ED 02EC 02ED 02EC 02ED 02EC 02ED 02E9 02ED 02EC 02ED 02EC 02ED
        02EE 02EF 02EE 02EF 02EE 02EF 02EE 02EF 02EE 02EF 02CB 02EF 02EE 02EF 02EE 02EF
        0044 01ED 0044 02C0 0044 0044 0044 0044 0044 0044 02E8 0044 0044 0044 0044 0044
        81FC 81FC 81FC 81FC 81FC 8D84 8D83 8D82 8D83 8983 8982 8983 8982 8D82 8D83 8983
        81E9 81FC 8116 81FC 81E9 8D66 8D65 8D62 8D63 8963 82C8 8963 8962 8D62 8D63 8963
        8176 81FC 81FC 81FC 8576 8566 8565 8044 8044 8044 82E7 8044 8044 8044 8044 8044
        8080 8044 8109 8044 8080 8586 8585 8044 8044 8044 82C7 8044 8044 8044 8044 8044
        8080 8044 8109 8044 8080 8568 8567 8044 8044 8044 82E7 8044 8044 8044 8044 8044
      </Screen>
          <Screen X="7" Y="0">
        8044 8044 8044 8187 8188 856F 816E 816F 856F 816E 816F 8586 8585 8044 8044 8044
        8162 8562 8563 8165 8166 856F 816E 816F 856F 816E 816F 8566 8565 8562 8561 8560
        8182 8582 85A3 8183 8184 856F 816E 816F 8579 8178 8179 8584 8583 8582 8581 8580
        0044 0044 02C7 0044 0044 8579 8178 8179 0044 81FC 81FC 09EE 09EF 0080 8566 8565
        0AEE 0AEF 02EB 0AEF 0AEE 0AEF 0AEE 0AEF 0AEE 81FC 81FC 0AEF 0AEE 0AEF 8586 8585
        02EC 02ED 02C9 02ED 02EC 02ED 02EC 02ED 02EC B116 B116 02ED 02EC 02ED 8568 8567
        02EE 02EF 02EA 02EF 02EE 02EF 02EE 02EF 02EE B116 02EE 02EF 02EE 02EF 8588 8587
        0AEE 0AEF 02CA 0AEF 0AEE 0AEF 0AEE 0AEF 0AEE B116 0AEE 0AEF 0AEE 0AEF 8568 8567
        02EC 02ED 02E9 02ED 02EC 02ED 02EC 02ED 02EC 02ED 02EC 02ED 816A 816B 816D 8587
        02EE 02EF 02CB 02EF 02EE 02EF 02EE 02EF 02EE 02EF 02EE 02EF 856F 896F 8566 8565
        0044 0044 02E8 0044 0044 0044 0044 0044 0044 0080 0080 0080 8D6F 816F 8584 8583
        8982 8983 8982 8D82 8D83 8983 8982 8983 8984 0080 0080 0080 8D6F 818E 816B 816B
        8962 8963 82C8 8D62 8D63 8963 8962 8965 8966 0080 0080 0080 856F 816E 8170 816E
        8044 8044 82E7 8044 8044 8044 8044 8165 8166 0080 0080 0080 856F 8970 816E 816E
        8044 8044 82C7 8044 8044 8044 8044 8185 8186 0080 0080 0080 856F 816E 816E 816E
        8044 8044 82E7 8044 8044 8044 8044 8167 8168 8109 8109 8109 8D6F 816E 816E 816E
      </Screen>
        </Layer1>
        <BTS>
          <Screen X="0" Y="0">
        00 00 00 00 00 00 00 00 00 00 00 00 00 00 00 00
        00 00 00 00 00 00 00 00 00 00 00 00 00 00 00 00
        00 00 00 00 00 00 00 00 00 00 00 00 00 00 00 00
        00 00 00 00 00 00 00 00 00 00 00 00 00 00 00 00
        00 00 00 00 00 00 00 00 00 00 00 00 00 00 04 04
        00 00 00 00 00 00 00 00 00 00 00 00 00 00 04 04
        00 00 00 00 00 00 00 00 00 00 00 00 00 00 00 00
        00 00 00 00 00 00 00 00 00 00 00 00 00 00 00 00
        00 00 00 00 00 00 00 00 00 00 00 00 00 00 00 00
        00 00 00 00 00 00 00 00 00 00 00 00 00 00 00 00
        00 00 00 00 00 00 42 FF FE FD 00 00 00 00 00 00
        00 00 00 00 00 00 00 00 00 00 00 00 00 00 00 00
        00 00 00 00 00 00 00 00 00 00 00 00 00 00 00 00
        00 00 00 00 00 00 00 00 00 00 00 00 00 00 00 00
        00 00 00 00 00 00 00 00 00 00 00 00 00 00 00 00
        00 00 00 00 00 00 00 00 00 00 00 00 00 00 00 00
      </Screen>
          <Screen X="1" Y="0">
        00 00 00 00 00 00 00 00 00 00 00 00 00 00 00 00
        00 00 00 00 00 00 00 00 00 00 00 00 00 00 00 00
        00 00 00 00 00 00 00 00 00 00 00 00 00 00 00 00
        00 00 00 00 00 00 00 00 00 00 00 00 00 00 00 00
        00 00 00 00 00 00 00 FF 00 00 00 00 00 00 00 00
        04 00 00 00 00 00 00 FE 00 00 00 00 00 00 00 00
        00 00 00 00 00 00 00 FD 00 00 00 00 00 00 00 00
        00 00 00 00 00 00 00 FC 00 00 00 00 00 00 00 00
        00 00 00 00 00 00 00 FB 00 00 00 00 00 00 00 00
        00 00 00 00 00 00 00 FA 00 00 00 00 00 00 00 00
        00 00 00 00 00 00 00 F9 00 00 00 00 00 00 00 00
        00 00 00 00 00 00 00 00 00 00 00 00 00 00 00 00
        00 00 00 00 00 00 00 00 00 00 00 00 00 00 00 00
        00 00 00 00 00 00 00 00 00 00 00 00 00 00 00 00
        00 00 00 00 00 00 00 00 00 00 00 00 00 00 00 00
        00 00 00 00 00 00 00 00 00 00 00 00 00 00 00 00
      </Screen>
          <Screen X="2" Y="0">
        00 00 00 00 00 00 00 00 00 00 00 00 00 00 00 00
        00 00 00 00 00 00 00 00 00 00 00 00 00 00 00 00
        00 00 00 00 00 00 00 00 00 00 00 00 00 00 00 00
        00 00 00 00 00 00 00 00 00 00 00 00 00 00 00 00
        00 00 00 00 00 00 00 00 00 00 00 00 00 00 00 00
        00 00 00 00 00 00 00 00 00 00 00 00 00 00 00 00
        00 00 00 00 00 00 00 00 00 00 00 00 00 00 00 00
        00 00 00 00 00 00 00 00 00 00 00 00 00 00 00 00
        00 00 00 00 00 00 00 00 00 00 00 00 00 00 00 00
        00 00 00 00 00 00 00 00 00 00 00 00 00 00 00 00
        00 00 00 00 00 00 00 00 00 00 00 00 00 00 00 00
        00 00 00 00 00 00 00 00 00 00 00 00 00 00 00 00
        00 00 00 00 00 00 00 00 00 00 00 00 00 00 00 00
        00 00 00 00 00 00 00 00 00 00 00 00 00 00 00 00
        00 00 00 00 00 00 00 00 00 00 00 00 00 00 00 00
        00 00 00 00 00 00 00 00 00 00 00 00 00 00 00 00
      </Screen>
          <Screen X="3" Y="0">
        00 00 00 00 00 00 01 01 01 01 00 00 00 00 00 00
        00 00 00 00 00 00 00 00 00 00 00 00 00 00 00 00
        00 00 00 00 00 00 43 FF FE FD 00 00 00 00 00 00
        00 00 00 00 00 00 00 00 00 00 00 00 00 00 00 00
        00 00 00 00 00 00 00 00 00 00 00 00 00 00 00 00
        00 00 00 00 00 00 00 00 00 00 00 00 00 00 00 00
        00 00 00 00 00 00 00 00 00 00 00 00 00 00 00 00
        00 00 00 00 00 00 00 00 00 00 00 00 00 00 00 00
        00 00 00 00 00 00 00 00 00 00 00 00 00 00 00 00
        00 00 00 00 00 00 00 00 00 00 00 00 00 00 00 00
        00 00 00 00 00 00 00 00 00 00 00 00 00 00 00 00
        00 00 00 00 00 00 00 00 00 00 00 00 00 00 00 00
        00 00 00 00 00 00 00 00 00 00 00 00 00 00 00 00
        00 00 00 00 00 00 00 00 00 00 00 00 00 00 00 00
        00 00 00 00 00 00 00 00 00 00 00 00 00 00 00 00
        00 00 00 00 00 00 00 00 00 00 00 00 00 00 00 00
      </Screen>
          <Screen X="4" Y="0">
        00 00 00 00 00 00 00 00 00 00 00 00 00 00 00 00
        00 00 00 00 00 00 00 00 00 00 00 00 00 00 00 00
        00 00 00 00 00 00 00 00 00 00 00 00 00 00 00 00
        00 00 00 00 00 00 00 00 00 00 00 00 00 00 00 00
        00 00 00 00 00 00 00 00 00 00 00 00 00 00 00 00
        00 00 00 00 00 00 00 00 00 00 00 00 00 00 00 00
        00 00 00 00 00 00 00 00 00 00 00 00 00 00 00 00
        00 00 00 00 00 00 00 00 00 00 00 00 00 00 00 00
        00 00 00 00 00 00 00 00 00 00 00 00 00 00 00 00
        00 00 00 00 00 00 00 00 00 00 00 00 00 00 00 00
        00 00 00 00 00 00 00 00 00 00 00 00 00 00 00 00
        00 00 00 00 00 00 00 00 00 00 00 00 00 00 00 00
        00 00 00 00 00 00 00 00 00 00 00 00 00 00 00 00
        00 00 00 00 00 00 00 00 00 00 00 00 00 00 00 00
        00 00 00 00 00 00 00 00 00 00 00 00 00 00 00 00
        00 00 00 00 00 00 00 00 00 00 00 00 00 00 00 00
      </Screen>
          <Screen X="5" Y="0">
        00 00 00 00 00 00 00 00 00 00 00 00 00 00 00 00
        00 00 00 00 00 00 00 00 00 00 00 00 00 00 00 00
        00 00 00 00 00 00 00 00 00 00 00 00 00 00 00 00
        00 00 00 00 00 00 00 00 00 00 00 00 00 00 00 00
        00 00 00 00 00 00 00 00 00 00 00 00 00 00 00 00
        00 00 00 00 00 00 00 00 00 00 00 00 00 00 00 00
        00 00 00 00 00 00 00 00 00 00 00 00 00 00 00 00
        00 00 00 00 00 00 00 00 00 00 00 00 00 00 00 00
        00 00 00 00 00 00 00 00 00 00 00 00 00 00 00 00
        00 00 00 00 00 00 00 00 00 00 00 00 00 00 00 00
        00 00 00 00 00 00 00 00 00 00 00 00 00 00 00 00
        00 00 00 00 00 00 00 00 00 00 00 00 00 00 00 00
        00 00 00 00 00 00 00 00 00 00 00 00 00 00 00 00
        00 00 00 00 00 00 00 00 00 00 00 00 00 00 00 00
        00 00 00 00 00 00 00 00 00 00 00 00 00 00 00 00
        00 00 00 00 00 00 00 00 00 00 00 00 00 00 00 00
      </Screen>
          <Screen X="6" Y="0">
        00 00 00 00 00 00 00 00 00 00 00 00 00 00 00 00
        00 00 00 00 00 00 00 00 00 00 00 00 00 00 00 00
        00 00 00 00 00 00 00 00 00 00 00 00 00 00 00 00
        00 00 00 00 00 00 00 00 00 00 00 00 00 00 00 00
        00 00 00 00 00 00 00 00 00 00 00 00 00 00 00 00
        00 00 00 00 00 00 00 00 00 00 00 00 00 00 00 00
        00 00 00 00 00 00 00 00 00 00 00 00 00 00 00 00
        00 00 00 00 00 00 00 00 00 00 00 00 00 00 00 00
        00 00 00 00 00 00 00 00 00 00 00 00 00 00 00 00
        00 00 00 00 00 00 00 00 00 00 00 00 00 00 00 00
        00 00 00 00 00 00 00 00 00 00 00 00 00 00 00 00
        00 00 00 00 00 00 00 00 00 00 00 00 00 00 00 00
        00 00 00 00 00 00 00 00 00 00 00 00 00 00 00 00
        00 00 00 00 00 00 00 00 00 00 00 00 00 00 00 00
        00 00 00 00 00 00 00 00 00 00 00 00 00 00 00 00
        00 00 00 00 00 00 00 00 00 00 00 00 00 00 00 00
      </Screen>
          <Screen X="7" Y="0">
        00 00 00 00 00 00 00 00 00 00 00 00 00 00 00 00
        00 00 00 00 00 00 00 00 00 00 00 00 00 00 00 00
        00 00 00 00 00 00 00 00 00 00 00 00 00 00 00 00
        00 00 00 00 00 00 00 00 00 00 00 00 00 00 00 00
        00 00 00 00 00 00 00 00 00 00 00 00 00 00 00 00
        00 00 00 00 00 00 00 00 00 0F 0F 00 00 00 00 00
        00 00 00 00 00 00 00 00 00 0F 00 00 00 00 00 00
        00 00 00 00 00 00 00 00 00 0F 00 00 00 00 00 00
        00 00 00 00 00 00 00 00 00 00 00 00 00 00 00 00
        00 00 00 00 00 00 00 00 00 00 00 00 00 00 00 00
        00 00 00 00 00 00 00 00 00 00 00 00 00 00 00 00
        00 00 00 00 00 00 00 00 00 00 00 00 00 00 00 00
        00 00 00 00 00 00 00 00 00 00 00 00 00 00 00 00
        00 00 00 00 00 00 00 00 00 00 00 00 00 00 00 00
        00 00 00 00 00 00 00 00 00 00 00 00 00 00 00 00
        00 00 00 00 00 00 00 00 00 00 00 00 00 00 00 00
      </Screen>
        </BTS>
      </LevelData>
      <GFXset>1B</GFXset>
      <music>0527</music>
      <FX1s>
        <FX1 default="true">
          <surfacestart>00C6</surfacestart>
          <surfacenew>FFFF</surfacenew>
          <surfacespeed>0000</surfacespeed>
          <surfacedelay>00</surfacedelay>
          <type>04</type>
          <transparency1_A>02</transparency1_A>
          <transparency2_B>02</transparency2_B>
          <liquidflags_C>81</liquidflags_C>
          <paletteflags>00</paletteflags>
          <animationflags>00</animationflags>
          <paletteblend>02</paletteblend>
        </FX1>
      </FX1s>
      <Enemies killcount="00">
        <Enemy>
          <ID>DDBF</ID>
          <X>0480</X>
          <Y>0078</Y>
          <tilemap>BD2A</tilemap>
          <special>2800</special>
          <gfx>0004</gfx>
          <speed>0000</speed>
          <speed2>0000</speed2>
        </Enemy>
        <Enemy>
          <ID>DDFF</ID>
          <X>0480</X>
          <Y>0078</Y>
          <tilemap>BD2A</tilemap>
          <special>A800</special>
          <gfx>0004</gfx>
          <speed>0000</speed>
          <speed2>0000</speed2>
        </Enemy>
      </Enemies>
      <EnemyTypes>
        <Enemy>
          <GFX>DDBF</GFX>
          <palette>D007</palette>
        </Enemy>
      </EnemyTypes>
      <layer2_type>BGData</layer2_type>
      <layer2_xscroll>00</layer2_xscroll>
      <layer2_yscroll>00</layer2_yscroll>
      <ScrollData>00 00 01 01 01 01 01 01 </ScrollData>
      <roomvar>0000</roomvar>
      <FX2>E8CD</FX2>
      <PLMs>
        <PLM>
          <type>C854</type>
          <x>36</x>
          <y>02</y>
          <arg>0069</arg>
        </PLM>
        <PLM>
          <type>EF47</type>
          <x>24</x>
          <y>0A</y>
          <arg>0056</arg>
        </PLM>
        <PLM>
          <type>FB00</type>
          <x>17</x>
          <y>03</y>
          <arg>A096</arg>
        </PLM>
        <PLM>
          <type>FB84</type>
          <x>00</x>
          <y>00</y>
          <arg>0005</arg>
        </PLM>
      </PLMs>
      <BGData>
        <Data Type="COPY">
          <SOURCE>7E2000</SOURCE>
          <DEST>4800</DEST>
          <SIZE>1000</SIZE>
        </Data>
      </BGData>
      <layer1_2>91F6</layer1_2>
    </State>
    <State condition="default">
      <LevelData Width="8" Height="1">
        <Layer1>
          <Screen X="0" Y="0">
        8044 8044 8044 8044 8044 8044 8044 8044 8044 8044 8044 8044 8044 8044 8044 8044
        8160 8161 8162 8562 8563 8163 8162 8163 8162 8562 8563 8562 8563 8163 8162 8163
        8180 8181 8182 8582 8583 8183 8182 8183 8182 8582 8583 8582 85A3 8183 8182 8183
        8165 8166 0044 0044 09EE 09EF 0080 0080 0080 09EE 09EF 0080 02C7 0080 0080 0080
        8185 8186 0044 0044 0044 0044 0044 0044 0044 0044 0044 0044 02E7 0044 F118 F118
        8167 8168 0AEE 0AEF 0AEE 0AEF 0AEE 0AEF 0AEE 0AEF 0AEE 0AEF 02E8 0044 F118 F118
        8187 8188 02EC 02ED 02EC 02ED 02EC 02ED 02EC 02ED 02EC 02ED 8D84 8D83 8D82 8D83
        8165 8166 02EC 02ED 02EC 02ED 02EC 02ED 02EC 02ED 02EC 02ED 8D66 8D65 8D62 8D63
        8167 8168 02EE 02EF 02EE 02EF 02EE 02EF 02EE 02EF 02EE 02EF 8566 8565 8044 8044
        8187 8981 8983 8984 0080 01ED 0044 0044 0044 0044 02C0 02E3 8586 8585 8044 8044
        8586 8585 8965 8966 81FC 81FC C41D 541C 501C 501D 81FC 81FC 8568 8567 8044 8044
        8568 8567 8165 8166 8109 8129 9443 9442 9042 9043 8109 8109 8588 8587 8044 8044
        8588 8587 8185 8186 8109 8129 8463 8462 8062 8063 8129 8129 8566 8565 8044 8044
        8566 8565 8167 8168 8129 8109 8463 8462 8062 8063 8129 8109 8586 8585 8044 8044
        8586 8585 8187 8188 8129 8109 8463 8462 8062 8063 8109 8109 8568 8567 8044 8044
        8568 8567 8165 8166 8109 8109 8463 8462 8062 8063 8109 8109 8588 8587 8044 8044
      </Screen>
          <Screen X="1" Y="0">
        8044 8044 8044 8044 8044 8044 8044 8044 8044 8044 8044 8044 8044 8187 8188 856F
        8162 8163 8162 8562 8563 8163 8162 8163 8162 8163 8162 8562 8563 8165 8166 856F
        8182 81A3 8182 8582 8583 8183 8182 8183 8182 81A3 8182 8582 8583 8183 8184 8579
        0080 02C7 0044 0044 0044 0044 0044 0044 0044 02C7 0044 09EE 09EF 0044 0044 0044
        0044 02E7 0044 0044 0044 0044 0044 D044 0044 02E7 0044 0044 0044 0044 0044 0044
        F118 02E8 0AEF 0AEE 0AEF 0AEE 0AEF DAEE 0AEF 030A 0044 0044 0044 0044 0044 0044
        8983 8984 02ED 02EC 02ED 02EC 02ED D2EC 02ED 0329 0044 0044 0044 0044 0044 0044
        8965 8966 02ED 02EC 02ED 02EC 02ED D2EC 02ED 0309 0044 0044 0044 0044 0044 0044
        8165 8166 02EF 02EE 02EF 02EE 02EF D2EE 02EF 032A 0044 0044 0044 0044 0044 0044
        8185 8186 0044 0044 0044 0044 0044 D044 0044 02C7 0044 0044 0044 0044 0044 0080
        8167 8168 0044 0044 0044 0044 0044 D044 0044 02E8 0044 0044 0044 0044 0080 0080
        8187 8188 0044 0044 8D84 8D83 8983 8982 8983 8982 8D82 8D83 8983 8982 8983 8984
        8165 8166 0044 0044 8D66 8D65 8963 8962 8963 82C8 8D62 8D63 8963 8962 8965 8966
        8185 8186 0044 0044 8566 8565 8044 8044 8044 82E7 8044 8044 8044 8044 8165 8166
        8167 8168 0080 0080 8586 8585 8044 8044 8044 82C7 8044 8044 8044 8044 8185 8186
        8187 8188 8109 8109 8568 8567 8044 8044 8044 82E7 8044 8044 8044 8044 8167 8168
      </Screen>
          <Screen X="2" Y="0">
        816E 816E 816E 816F 8588 8587 8044 8044 8044 8044 8044 8044 8044 8044 8044 8044
        816E 816E 816E 816F 8566 8565 8562 8563 8562 8563 8163 8162 8163 8162 8562 8563
        8178 8178 8178 8179 8584 8583 8582 8583 8582 85A3 8183 8182 8183 8182 8582 8583
        8165 8100 A101 0044 0080 09EE 09EF 0044 0080 02C7 0080 0044 09EE 09EF 0044 0044
        8185 8120 A121 0044 0044 0044 0044 0044 0044 034A 0AEF 0AEE 0AEE 0AEF 0AEE 0AEF
        8165 8100 A101 0044 0044 0044 0044 0044 0044 0349 02ED 02EC 02EC 02ED 02EC 02ED
        8185 8120 A121 0044 0044 0044 0044 0044 0044 036A 02EF 02EE 02EE 02EF 02EE 02EF
        8165 8100 A101 0044 0044 0044 0044 0044 0044 036B 0AEF 0AEE 0AEE 0AEF 0AEE 0AEF
        8185 8120 A121 0044 0044 0044 0044 0044 0044 0369 02ED 02EC 02EC 02ED 02EC 02ED
        8165 8100 A101 0044 0080 02C2 0080 0044 0080 034B 02EF 02EE 02EE 02EF 02EE 02EF
        8185 8120 A121 0044 0044 02E2 0044 0044 0044 02E7 0044 0044 0044 0080 0044 0044
        8171 816B 856B 856A 805D 8169 8D84 8D83 8983 8982 8983 8982 8D82 8D83 8983 8982
        856F 816E 816E 8170 8978 8189 8D66 8D65 8963 82C8 8963 8962 8D62 8D63 8963 8962
        856F 816E 8970 816E 816E 816F 8566 8565 8044 82E7 8044 8044 8044 8044 8044 8044
        856F 816E 816E 816E 816E 816F 8586 8585 8044 82C7 8044 8044 8044 8044 8044 8044
        856F 816E 816E 816E 816E 816F 8568 8567 8044 82E7 8044 8044 8044 8044 8044 8044
      </Screen>
          <Screen X="3" Y="0">
        8044 8044 8044 8044 8185 8186 9C63 9C62 9862 9863 8588 8587 8044 8044 8044 8044
        8163 8162 8562 8563 8165 8166 2C43 2C42 2842 2843 8566 8565 8562 8563 8562 8563
        8183 8182 8582 8583 8183 8184 CC1D 5C1C 581C 581D 8584 8583 8582 85A3 8582 8583
        0044 0044 0044 0044 0044 0044 0044 0044 0044 0044 0044 0044 0044 02C7 09EE 09EF
        0AEE 0AEF 0AEE 0AEF 0AEE 0AEF 0AEE 0AEF 0AEE 0AEF 0AEE 0AEE 0AEF 02EB 0AEF 0AEE
        02EC 02ED 02EC 02ED 02EC 02ED 02EC 02ED 02EC 02ED 02EC 02EC 02ED 02C9 02ED 02EC
        02EE 02EF 02EE 02EF 02EE 02EF 02EE 02EF 02EE 02EF 02EE 02EE 02EF 02EA 02EF 02EE
        0AEE 0AEF 0AEE 0AEF 0AEE 0AEF 0AEE 0AEF 0AEE 0AEF 0AEE 0AEE 0AEF 02CA 0AEF 0AEE
        02EC 02ED 02EC 02ED 02EC 02ED 02EC 02ED 02EC 02ED 02EC 02EC 02ED 02E9 02ED 02EC
        02EE 02EF 02EE 02EF 02EE 02EF 02EE 02EF 02EE 02EF 02EE 02EE 02EF 02CB 02EF 02EE
        0044 0044 0044 0044 0044 0044 0044 0044 0044 0044 0044 0044 0044 02E8 0044 0044
        8983 8982 8D82 8D83 8983 8982 8D82 8D83 8983 8982 8983 8982 8983 8982 8983 8984
        8963 82C8 8D62 8D63 8963 8962 8D62 8D63 8963 82C8 8963 8962 8963 82C8 8965 8966
        8044 82E7 8044 8044 8044 8044 8044 8044 8044 82E7 8044 8044 8044 82E7 8165 8166
        8044 82C7 8044 8044 8044 8044 8044 8044 8044 82C7 8044 8044 8044 82C7 8185 8186
        8044 82E7 8044 8044 8044 8044 8044 8044 8044 82E7 8044 8044 8044 82E7 8167 8168
      </Screen>
          <Screen X="4" Y="0">
        8044 8044 8044 8044 8044 8044 8044 8044 8044 8044 8044 8044 8044 8044 8044 8044
        8163 8162 8163 8162 8562 8563 8562 8563 8163 8162 8562 8563 8163 8162 8562 8563
        8183 8182 8183 8182 8582 8583 8582 85A3 8183 8182 8582 8583 8183 8182 8582 8583
        0044 0044 0044 0044 0044 0044 0044 02C7 0044 0044 09EE 09EF 0044 0044 0044 0044
        0AEE 0AEF 0AEE 0AEF 0AEE 0AEE 0AEF 02EB 0AEF 0AEE 0AEE 0AEF 0AEE 0AEF 0AEE 0AEF
        02EC 02ED 02EC 02ED 02EC 02EC 02ED 02C9 02ED 02EC 02EC 02ED 02EC 02ED 02EC 02ED
        02EE 02EF 02EE 02EF 02EE 02EE 02EF 02EA 02EF 02EE 02EE 02EF 02EE 02EF 02EE 02EF
        0AEE 0AEF 0AEE 0AEF 0AEE 0AEE 0AEF 02CA 0AEF 0AEE 0AEE 0AEF 0AEE 0AEF 0AEE 0AEF
        02EC 02ED 02EC 02ED 02EC 02EC 02ED 02E9 02ED 02EC 02EC 02ED 02EC 02ED 02EC 02ED
        02EE 02EF 02EE 02EF 02EE 02EE 02EF 02CB 02EF 02EE 02EE 02EF 02EE 02EF 02EE 02EF
        0044 02E3 06E3 02C0 02E3 0044 0044 02E8 0044 0044 0044 0044 0044 0044 0044 01ED
        81FC 81FC 81FC 81FC 81FC 81FC 8983 8D83 8983 8982 8983 8982 8983 8984 81FC 81FC
        8129 8177 8176 8177 8176 8109 8D66 8D65 8963 8962 8963 8962 8965 8966 8176 82CB
        8109 8044 8044 8044 8044 8129 8566 8565 8044 8044 8044 8044 8165 8166 8044 82E7
        8109 8044 8044 8044 8044 8129 8586 8585 8044 8044 8044 8044 8185 8186 8044 82C7
        8109 8044 8044 8044 8044 8109 8568 8567 8044 8044 8044 8044 8167 8168 8044 82E7
      </Screen>
          <Screen X="5" Y="0">
        8044 8044 8044 8044 8044 8044 8044 8044 8187 8188 856F 816E 816F 0586 8585 8044
        8163 8162 8163 8162 8562 8563 8163 8162 8165 8166 856F 816E 816F 8566 8565 8163
        8183 8182 8183 8182 8582 8583 8183 8182 8183 8184 856F 816E 816F 8584 8583 8183
        0044 09EE 09EF 0044 0044 0044 0044 0044 0044 0044 8579 8178 8179 0044 0044 09EE
        0AEE 0AEF 0AEE 0AEF 0AEE 0AEF 0AEE 0AEF 0AEE 0AEF 0AEE 02EB 0AEE 0AEF 0AEE 0AEF
        02EC 02ED 02EC 02ED 02EC 02ED 02EC 02ED 02EC 02ED 02EC 02C9 02EC 02ED 02EC 02ED
        02EE 02EF 02EE 02EF 02EE 02EF 02EE 02EF 02EE 02EF 02EE 02EA 02EE 02EF 02EE 02EF
        0AEE 0AEF 0AEE 0AEF 0AEE 0AEF 0AEE 0AEF 0AEE 0AEF 0AEE 02CA 0AEE 0AEF 0AEE 0AEF
        02EC 02ED 02EC 02ED 02EC 02ED 02EC 02ED 02EC 02ED 02EC 02E9 02EC 02ED 02EC 02ED
        02EE 02EF 02EE 02EF 02EE 02EF 02EE 02EF 02EE 02EF 02EE 02CB 02EE 02EF 02EE 02EF
        0044 06E3 02E3 02E3 0044 0044 0044 0044 0044 0044 0044 02E8 0044 0044 0044 0044
        81FC 81FC 81FC 81FC 8D84 8D83 8983 8982 8983 8982 8983 8982 8983 8982 8983 8984
        81E9 81E9 82CB 8577 8D66 8D65 8963 8962 8963 8962 8963 82C8 8963 8962 8965 8966
        8044 8044 82E7 8444 8566 8565 8044 8044 8044 8044 8044 82E7 8044 8044 8165 8166
        8044 8044 82C7 8044 8586 8585 8044 8044 8044 8044 8044 82C7 8044 8044 8185 8186
        8044 8044 82E7 8044 8568 8567 8044 8044 8044 8044 8044 82E7 8044 8044 8167 8168
      </Screen>
          <Screen X="6" Y="0">
        8044 8044 8044 8044 8044 8044 8044 8044 8044 8044 8044 8044 8044 8044 8044 8044
        8162 8163 8162 8562 8563 8163 8162 8163 8162 8163 8162 8562 8563 8562 8563 8163
        8182 8183 8182 8582 8583 8183 8182 8183 8182 8183 85A3 8582 8583 8582 8583 8183
        09EF 0044 0044 0044 0044 0044 09EE 09EF 0044 0044 02C7 0044 0044 0044 0044 0044
        0AEE 0AEF 0AEE 0AEF 0AEE 0AEF 0AEE 0AEF 0AEE 0AEF 02EB 0AEF 0AEE 0AEF 0AEE 0AEF
        02EC 02ED 02EC 02ED 02EC 02ED 02EC 02ED 02EC 02ED 02C9 02ED 02EC 02ED 02EC 02ED
        02EE 02EF 02EE 02EF 02EE 02EF 02EE 02EF 02EE 02EF 02EA 02EF 02EE 02EF 02EE 02EF
        0AEE 0AEF 0AEE 0AEF 0AEE 0AEF 0AEE 0AEF 0AEE 0AEF 02CA 0AEF 0AEE 0AEF 0AEE 0AEF
        02EC 02ED 02EC 02ED 02EC 02ED 02EC 02ED 02EC 02ED 02E9 02ED 02EC 02ED 02EC 02ED
        02EE 02EF 02EE 02EF 02EE 02EF 02EE 02EF 02EE 02EF 02CB 02EF 02EE 02EF 02EE 02EF
        0044 01ED 0044 02C0 0044 0044 0044 0044 0044 0044 02E8 0044 0044 0044 0044 0044
        81FC 81FC 81FC 81FC 81FC 8D84 8D83 8D82 8D83 8983 8982 8983 8982 8D82 8D83 8983
        81E9 81FC 8116 81FC 81E9 8D66 8D65 8D62 8D63 8963 82C8 8963 8962 8D62 8D63 8963
        8176 81FC 81FC 81FC 8576 8566 8565 8044 8044 8044 82E7 8044 8044 8044 8044 8044
        8080 8044 8109 8044 8080 8586 8585 8044 8044 8044 82C7 8044 8044 8044 8044 8044
        8080 8044 8109 8044 8080 8568 8567 8044 8044 8044 82E7 8044 8044 8044 8044 8044
      </Screen>
          <Screen X="7" Y="0">
        8044 8044 8044 8187 8188 856F 816E 816F 856F 816E 816F 8586 8585 8044 8044 8044
        8162 8562 8563 8165 8166 856F 816E 816F 856F 816E 816F 8566 8565 8562 8561 8560
        8182 8582 85A3 8183 8184 856F 816E 816F 8579 8178 8179 8584 8583 8582 8581 8580
        0044 0044 02C7 0044 0044 8579 8178 8179 0044 81FC 81FC 09EE 09EF 0080 8566 8565
        0AEE 0AEF 02EB 0AEF 0AEE 0AEF 0AEE 0AEF 0AEE 81FC 81FC 0AEF 0AEE 0AEF 8586 8585
        02EC 02ED 02C9 02ED 02EC 02ED 02EC 02ED 02EC B116 B116 02ED 02EC 02ED 8568 8567
        02EE 02EF 02EA 02EF 02EE 02EF 02EE 02EF 02EE B116 02EE 02EF 02EE 02EF 8588 8587
        0AEE 0AEF 02CA 0AEF 0AEE 0AEF 0AEE 0AEF 0AEE B116 0AEE 0AEF 0AEE 0AEF 8568 8567
        02EC 02ED 02E9 02ED 02EC 02ED 02EC 02ED 02EC 02ED 02EC 02ED 816A 816B 816D 8587
        02EE 02EF 02CB 02EF 02EE 02EF 02EE 02EF 02EE 02EF 02EE 02EF 856F 896F 8566 8565
        0044 0044 02E8 0044 0044 0044 0044 0044 0044 0080 0080 0080 8D6F 816F 8584 8583
        8982 8983 8982 8D82 8D83 8983 8982 8983 8984 0080 0080 0080 8D6F 818E 816B 816B
        8962 8963 82C8 8D62 8D63 8963 8962 8965 8966 0080 0080 0080 856F 816E 8170 816E
        8044 8044 82E7 8044 8044 8044 8044 8165 8166 0080 0080 0080 856F 8970 816E 816E
        8044 8044 82C7 8044 8044 8044 8044 8185 8186 0080 0080 0080 856F 816E 816E 816E
        8044 8044 82E7 8044 8044 8044 8044 8167 8168 8109 8109 8109 8D6F 816E 816E 816E
      </Screen>
        </Layer1>
        <BTS>
          <Screen X="0" Y="0">
        00 00 00 00 00 00 00 00 00 00 00 00 00 00 00 00
        00 00 00 00 00 00 00 00 00 00 00 00 00 00 00 00
        00 00 00 00 00 00 00 00 00 00 00 00 00 00 00 00
        00 00 00 00 00 00 00 00 00 00 00 00 00 00 00 00
        00 00 00 00 00 00 00 00 00 00 00 00 00 00 04 04
        00 00 00 00 00 00 00 00 00 00 00 00 00 00 04 04
        00 00 00 00 00 00 00 00 00 00 00 00 00 00 00 00
        00 00 00 00 00 00 00 00 00 00 00 00 00 00 00 00
        00 00 00 00 00 00 00 00 00 00 00 00 00 00 00 00
        00 00 00 00 00 00 00 00 00 00 00 00 00 00 00 00
        00 00 00 00 00 00 42 FF FE FD 00 00 00 00 00 00
        00 00 00 00 00 00 00 00 00 00 00 00 00 00 00 00
        00 00 00 00 00 00 00 00 00 00 00 00 00 00 00 00
        00 00 00 00 00 00 00 00 00 00 00 00 00 00 00 00
        00 00 00 00 00 00 00 00 00 00 00 00 00 00 00 00
        00 00 00 00 00 00 00 00 00 00 00 00 00 00 00 00
      </Screen>
          <Screen X="1" Y="0">
        00 00 00 00 00 00 00 00 00 00 00 00 00 00 00 00
        00 00 00 00 00 00 00 00 00 00 00 00 00 00 00 00
        00 00 00 00 00 00 00 00 00 00 00 00 00 00 00 00
        00 00 00 00 00 00 00 00 00 00 00 00 00 00 00 00
        00 00 00 00 00 00 00 FF 00 00 00 00 00 00 00 00
        04 00 00 00 00 00 00 FE 00 00 00 00 00 00 00 00
        00 00 00 00 00 00 00 FD 00 00 00 00 00 00 00 00
        00 00 00 00 00 00 00 FC 00 00 00 00 00 00 00 00
        00 00 00 00 00 00 00 FB 00 00 00 00 00 00 00 00
        00 00 00 00 00 00 00 FA 00 00 00 00 00 00 00 00
        00 00 00 00 00 00 00 F9 00 00 00 00 00 00 00 00
        00 00 00 00 00 00 00 00 00 00 00 00 00 00 00 00
        00 00 00 00 00 00 00 00 00 00 00 00 00 00 00 00
        00 00 00 00 00 00 00 00 00 00 00 00 00 00 00 00
        00 00 00 00 00 00 00 00 00 00 00 00 00 00 00 00
        00 00 00 00 00 00 00 00 00 00 00 00 00 00 00 00
      </Screen>
          <Screen X="2" Y="0">
        00 00 00 00 00 00 00 00 00 00 00 00 00 00 00 00
        00 00 00 00 00 00 00 00 00 00 00 00 00 00 00 00
        00 00 00 00 00 00 00 00 00 00 00 00 00 00 00 00
        00 00 00 00 00 00 00 00 00 00 00 00 00 00 00 00
        00 00 00 00 00 00 00 00 00 00 00 00 00 00 00 00
        00 00 00 00 00 00 00 00 00 00 00 00 00 00 00 00
        00 00 00 00 00 00 00 00 00 00 00 00 00 00 00 00
        00 00 00 00 00 00 00 00 00 00 00 00 00 00 00 00
        00 00 00 00 00 00 00 00 00 00 00 00 00 00 00 00
        00 00 00 00 00 00 00 00 00 00 00 00 00 00 00 00
        00 00 00 00 00 00 00 00 00 00 00 00 00 00 00 00
        00 00 00 00 00 00 00 00 00 00 00 00 00 00 00 00
        00 00 00 00 00 00 00 00 00 00 00 00 00 00 00 00
        00 00 00 00 00 00 00 00 00 00 00 00 00 00 00 00
        00 00 00 00 00 00 00 00 00 00 00 00 00 00 00 00
        00 00 00 00 00 00 00 00 00 00 00 00 00 00 00 00
      </Screen>
          <Screen X="3" Y="0">
        00 00 00 00 00 00 01 01 01 01 00 00 00 00 00 00
        00 00 00 00 00 00 00 00 00 00 00 00 00 00 00 00
        00 00 00 00 00 00 43 FF FE FD 00 00 00 00 00 00
        00 00 00 00 00 00 00 00 00 00 00 00 00 00 00 00
        00 00 00 00 00 00 00 00 00 00 00 00 00 00 00 00
        00 00 00 00 00 00 00 00 00 00 00 00 00 00 00 00
        00 00 00 00 00 00 00 00 00 00 00 00 00 00 00 00
        00 00 00 00 00 00 00 00 00 00 00 00 00 00 00 00
        00 00 00 00 00 00 00 00 00 00 00 00 00 00 00 00
        00 00 00 00 00 00 00 00 00 00 00 00 00 00 00 00
        00 00 00 00 00 00 00 00 00 00 00 00 00 00 00 00
        00 00 00 00 00 00 00 00 00 00 00 00 00 00 00 00
        00 00 00 00 00 00 00 00 00 00 00 00 00 00 00 00
        00 00 00 00 00 00 00 00 00 00 00 00 00 00 00 00
        00 00 00 00 00 00 00 00 00 00 00 00 00 00 00 00
        00 00 00 00 00 00 00 00 00 00 00 00 00 00 00 00
      </Screen>
          <Screen X="4" Y="0">
        00 00 00 00 00 00 00 00 00 00 00 00 00 00 00 00
        00 00 00 00 00 00 00 00 00 00 00 00 00 00 00 00
        00 00 00 00 00 00 00 00 00 00 00 00 00 00 00 00
        00 00 00 00 00 00 00 00 00 00 00 00 00 00 00 00
        00 00 00 00 00 00 00 00 00 00 00 00 00 00 00 00
        00 00 00 00 00 00 00 00 00 00 00 00 00 00 00 00
        00 00 00 00 00 00 00 00 00 00 00 00 00 00 00 00
        00 00 00 00 00 00 00 00 00 00 00 00 00 00 00 00
        00 00 00 00 00 00 00 00 00 00 00 00 00 00 00 00
        00 00 00 00 00 00 00 00 00 00 00 00 00 00 00 00
        00 00 00 00 00 00 00 00 00 00 00 00 00 00 00 00
        00 00 00 00 00 00 00 00 00 00 00 00 00 00 00 00
        00 00 00 00 00 00 00 00 00 00 00 00 00 00 00 00
        00 00 00 00 00 00 00 00 00 00 00 00 00 00 00 00
        00 00 00 00 00 00 00 00 00 00 00 00 00 00 00 00
        00 00 00 00 00 00 00 00 00 00 00 00 00 00 00 00
      </Screen>
          <Screen X="5" Y="0">
        00 00 00 00 00 00 00 00 00 00 00 00 00 00 00 00
        00 00 00 00 00 00 00 00 00 00 00 00 00 00 00 00
        00 00 00 00 00 00 00 00 00 00 00 00 00 00 00 00
        00 00 00 00 00 00 00 00 00 00 00 00 00 00 00 00
        00 00 00 00 00 00 00 00 00 00 00 00 00 00 00 00
        00 00 00 00 00 00 00 00 00 00 00 00 00 00 00 00
        00 00 00 00 00 00 00 00 00 00 00 00 00 00 00 00
        00 00 00 00 00 00 00 00 00 00 00 00 00 00 00 00
        00 00 00 00 00 00 00 00 00 00 00 00 00 00 00 00
        00 00 00 00 00 00 00 00 00 00 00 00 00 00 00 00
        00 00 00 00 00 00 00 00 00 00 00 00 00 00 00 00
        00 00 00 00 00 00 00 00 00 00 00 00 00 00 00 00
        00 00 00 00 00 00 00 00 00 00 00 00 00 00 00 00
        00 00 00 00 00 00 00 00 00 00 00 00 00 00 00 00
        00 00 00 00 00 00 00 00 00 00 00 00 00 00 00 00
        00 00 00 00 00 00 00 00 00 00 00 00 00 00 00 00
      </Screen>
          <Screen X="6" Y="0">
        00 00 00 00 00 00 00 00 00 00 00 00 00 00 00 00
        00 00 00 00 00 00 00 00 00 00 00 00 00 00 00 00
        00 00 00 00 00 00 00 00 00 00 00 00 00 00 00 00
        00 00 00 00 00 00 00 00 00 00 00 00 00 00 00 00
        00 00 00 00 00 00 00 00 00 00 00 00 00 00 00 00
        00 00 00 00 00 00 00 00 00 00 00 00 00 00 00 00
        00 00 00 00 00 00 00 00 00 00 00 00 00 00 00 00
        00 00 00 00 00 00 00 00 00 00 00 00 00 00 00 00
        00 00 00 00 00 00 00 00 00 00 00 00 00 00 00 00
        00 00 00 00 00 00 00 00 00 00 00 00 00 00 00 00
        00 00 00 00 00 00 00 00 00 00 00 00 00 00 00 00
        00 00 00 00 00 00 00 00 00 00 00 00 00 00 00 00
        00 00 00 00 00 00 00 00 00 00 00 00 00 00 00 00
        00 00 00 00 00 00 00 00 00 00 00 00 00 00 00 00
        00 00 00 00 00 00 00 00 00 00 00 00 00 00 00 00
        00 00 00 00 00 00 00 00 00 00 00 00 00 00 00 00
      </Screen>
          <Screen X="7" Y="0">
        00 00 00 00 00 00 00 00 00 00 00 00 00 00 00 00
        00 00 00 00 00 00 00 00 00 00 00 00 00 00 00 00
        00 00 00 00 00 00 00 00 00 00 00 00 00 00 00 00
        00 00 00 00 00 00 00 00 00 00 00 00 00 00 00 00
        00 00 00 00 00 00 00 00 00 00 00 00 00 00 00 00
        00 00 00 00 00 00 00 00 00 0F 0F 00 00 00 00 00
        00 00 00 00 00 00 00 00 00 0F 00 00 00 00 00 00
        00 00 00 00 00 00 00 00 00 0F 00 00 00 00 00 00
        00 00 00 00 00 00 00 00 00 00 00 00 00 00 00 00
        00 00 00 00 00 00 00 00 00 00 00 00 00 00 00 00
        00 00 00 00 00 00 00 00 00 00 00 00 00 00 00 00
        00 00 00 00 00 00 00 00 00 00 00 00 00 00 00 00
        00 00 00 00 00 00 00 00 00 00 00 00 00 00 00 00
        00 00 00 00 00 00 00 00 00 00 00 00 00 00 00 00
        00 00 00 00 00 00 00 00 00 00 00 00 00 00 00 00
        00 00 00 00 00 00 00 00 00 00 00 00 00 00 00 00
      </Screen>
        </BTS>
      </LevelData>
      <GFXset>1B</GFXset>
      <music>0527</music>
      <FX1s>
        <FX1 default="true">
          <surfacestart>00C6</surfacestart>
          <surfacenew>FFFF</surfacenew>
          <surfacespeed>0000</surfacespeed>
          <surfacedelay>00</surfacedelay>
          <type>04</type>
          <transparency1_A>02</transparency1_A>
          <transparency2_B>02</transparency2_B>
          <liquidflags_C>81</liquidflags_C>
          <paletteflags>00</paletteflags>
          <animationflags>00</animationflags>
          <paletteblend>02</paletteblend>
        </FX1>
      </FX1s>
      <Enemies killcount="00">
        <Enemy>
          <ID>DDBF</ID>
          <X>0480</X>
          <Y>0078</Y>
          <tilemap>BD2A</tilemap>
          <special>2800</special>
          <gfx>0004</gfx>
          <speed>0000</speed>
          <speed2>0000</speed2>
        </Enemy>
        <Enemy>
          <ID>DDFF</ID>
          <X>0480</X>
          <Y>0078</Y>
          <tilemap>BD2A</tilemap>
          <special>A800</special>
          <gfx>0004</gfx>
          <speed>0000</speed>
          <speed2>0000</speed2>
        </Enemy>
      </Enemies>
      <EnemyTypes>
        <Enemy>
          <GFX>DDBF</GFX>
          <palette>D007</palette>
        </Enemy>
      </EnemyTypes>
      <layer2_type>BGData</layer2_type>
      <layer2_xscroll>00</layer2_xscroll>
      <layer2_yscroll>00</layer2_yscroll>
      <ScrollData>00 00 01 01 01 01 01 01 </ScrollData>
      <roomvar>0000</roomvar>
      <FX2>E8CD</FX2>
      <PLMs>
        <PLM>
          <type>C854</type>
          <x>36</x>
          <y>02</y>
          <arg>0069</arg>
        </PLM>
        <PLM>
          <type>EF4B</type>
          <x>24</x>
          <y>0A</y>
          <arg>0056</arg>
        </PLM>
        <PLM>
          <type>FB00</type>
          <x>17</x>
          <y>03</y>
          <arg>A096</arg>
        </PLM>
        <PLM>
          <type>FB84</type>
          <x>00</x>
          <y>00</y>
          <arg>0005</arg>
        </PLM>
      </PLMs>
      <BGData>
        <Data Type="COPY">
          <SOURCE>7E2000</SOURCE>
          <DEST>4800</DEST>
          <SIZE>1000</SIZE>
        </Data>
      </BGData>
      <layer1_2>91F6</layer1_2>
    </State>
  </States>
</Room>