<Room>
  <Saves />
  <index>85</index>
  <area>02</area>
  <x>13</x>
  <y>0D</y>
  <width>04</width>
  <height>03</height>
  <upscroll>70</upscroll>
  <dnscroll>70</dnscroll>
  <specialGFX>00</specialGFX>
  <Doors>
    <Door>
      <toroom area="02" index="7F" />
      <bitflag>00</bitflag>
      <direction>05</direction>
      <tilex>E</tilex>
      <tiley>6</tiley>
      <screenx>00</screenx>
      <screeny>03</screeny>
      <distance>8000</distance>
      <doorcode>0000</doorcode>
    </Door>
    <Door>
      <toroom area="02" index="86" />
      <bitflag>00</bitflag>
      <direction>04</direction>
      <tilex>1</tilex>
      <tiley>6</tiley>
      <screenx>01</screenx>
      <screeny>01</screeny>
      <distance>8000</distance>
      <doorcode>0000</doorcode>
    </Door>
  </Doors>
  <States>
    <State condition="default">
      <LevelData Width="4" Height="3">
        <Layer1>
          <Screen X="0" Y="0">
        8180 8180 8180 8180 8180 8180 8180 8180 8180 8180 8180 8180 8180 8180 8180 8180
        8180 8180 8180 8180 8180 8180 8180 8180 8180 8180 8180 8180 8180 8180 8180 8180
        8180 8180 8180 8180 8180 8180 8180 8180 8180 8180 8180 8180 81A0 8181 85A0 8180
        8180 8180 8180 81A0 81A1 8186 8187 83B1 83B0 83B0 83B1 83B2 8188 8189 85A1 8180
        8180 8561 81A1 1186 1187 11A6 11A7 00FF 00FF 00FF 00FF 00FF 11A8 11A9 83B3 8161
        83B1 83B1 13B1 11A6 11A7 00FF 00FF 00FF 00FF 00FF 00FF 00FF 00FF 00FF 82EF 8181
        9440 C40C 00FF 00FF 00FF 00FF 00FF 00FF 00FF 00FF 00FF 00FF 00FF 00FF 82EF 85A1
        9460 D42C 00FF 00FF 00FF 00FF 00FF 00FF 00FF 00FF 00FF 00FF 00FF 00FF 82EF 8182
        9C60 DC2C 00FF 00FF 00FF 00FF 00FF 00FF 00FF 00FF 00FF 00FF 00FF 00FF 83AF 83B0
        9C40 DC0C 00FF 00FF 00FF 00FF 00FF 00FF 00FF 00FF 00FF 00FF 00FF 00FF 00FF 2321
        822B 8226 8229 822A 8545 82E1 8761 8365 00FF 00FF 00FF 00FF 00FF 00FF 00FF 2320
        8180 8180 8180 8609 80FF 8725 8302 1385 00FF 00FF 00FF 00FF 00FF 00FF E09B E09B
        8180 8180 8180 878F 1724 1723 00FF 00FF 00FF 00FF 00FF 00FF 00FF 00FF 00FF 00FF
        8180 8180 8180 86EF 00FF 00FF 00FF 00FF 00FF 00FF 00FF 00FF 00FF 00FF 00FF 00FF
        8180 8180 8180 86EF 00FF 00FF 00FF 00FF 00FF 00FF 00FF 00FF 00FF 00FF 00FF 00FF
        8180 8584 8180 86EF 00FF 00FF 00FF 00FF 00FF 00FF 00FF 00FF 00FF 00FF 00FF 00FF
      </Screen>
          <Screen X="1" Y="0">
        8180 8180 8180 8180 8180 8180 8180 8180 8180 8180 8180 8180 8180 86EF 00FF 82EF
        8180 8180 8180 8180 8180 8180 8180 8180 8180 8180 8180 8180 8180 86EF 00FF 82EF
        8180 8180 8180 8180 8180 8180 8180 8180 8180 8180 8180 8180 8180 864F 00FF 82EF
        8180 8180 8180 8180 8180 8180 8180 8180 8180 8180 8180 8180 8180 868F 00FF 83AF
        8180 8180 8160 8160 8180 8180 8180 8180 8180 8180 8180 8180 8180 86CF 80E4 00FF
        81A0 8181 8181 8181 8181 85A0 8180 8180 8180 8180 8180 8180 8180 87D3 822B 822B
        87B3 83B1 8188 8189 8182 85A1 85A0 8180 8180 8180 8180 8180 8180 8180 8180 8180
        86EF 00FF 11A8 11A9 1188 1189 85A1 8180 8180 8180 8180 8180 8180 8180 81A0 8161
        87AF 00FF 00FF 00FF 11A8 11A9 83B3 8180 8180 8180 8180 8180 81A0 8181 8181 85A1
        00FF 00FF 00FF 00FF 00FF 00FF 82EF 8180 8180 8180 8180 87B3 83B1 8188 8189 8182
        00FF 00FF 00FF 00FF 00FF 00FF 82EF 8180 8180 8180 8180 86EF 00FF 11A8 11A9 1188
        E09B 00FF 00FF 00FF 00FF 00FF 82EF 8180 8180 8180 8180 86EF 00FF 00FF 00FF 11A8
        00FF 00FF 00FF 00FF 00FF 00FF 83AF 83B0 83B0 83B1 83B0 87AF 00FF 00FF 00FF 00FF
        00FF 00FF 00FF 00FF 00FF 00FF 00FF 2321 00FF 00FF 2321 00FF 00FF 00FF 00FF 00FF
        00FF 00FF 00FF 00FF 00FF 00FF 00FF 2320 00FF 00FF 2320 00FF 00FF 00FF 00FF 00FF
        00FF 00FF 00FF 00FF 00FF 00FF 00FF E09B E09B E09B E09B 00FF 00FF 00FF 00FF 00FF
      </Screen>
          <Screen X="2" Y="0">
        8180 8180 8180 8180 8180 8180 8180 8180 8180 8180 8180 8180 8180 8180 8180 8180
        8180 8180 8180 8180 8180 8180 87B3 83B0 83B0 83B0 83B1 83B0 83B1 83B0 83B1 83B0
        8180 8180 8180 8180 8180 8180 878F 82EA 86EA E09B E09B E09B 82EA 82EB 82EB 82EB
        83B0 83B0 83B0 8A26 8A29 8A2A 87AF 00FF 00FF 00FF 00FF 00FF 00FF 00FF 00FF 00FF
        00FF 00FF 00FF 00FF 00FF 00FF 00FF 00FF 00FF 00FF 00FF 00FF 00FF 00FF 00FF 00FF
        8226 8229 8227 8229 822A 822F E09B 00FF 00FF 00FF 00FF 00FF 00FF 00FF 00FF 00FF
        8180 8180 8180 8180 8180 878F E09B 00FF 00FF 00FF 00FF 00FF 00FF 00FF 00FF 00FF
        8180 8180 8180 8180 8180 878F E09B 00FF 00FF 00FF 00FF 00FF 00FF 00FF 00FF 00FF
        8161 8180 8180 8180 8180 878F E09B 00FF 00FF 00FF 00FF 00FF 00FF 00FF 00FF 00FF
        85A1 85A0 8180 8180 8180 864F E09B 00FF 00FF 00FF 00FF 00FF 00FF 00FF 8765 82E1
        1189 85A1 8180 8180 8180 868F E09B 00FF 00FF 00FF 00FF 00FF 00FF 00FF 8785 8301
        11A9 83B3 8180 8180 8180 868F E09B 00FF 00FF 00FF 00FF 00FF 00FF 00FF E09B 80FF
        00FF 82EF 8180 8180 8180 86CF E09B 00FF 00FF 00FF 00FF 00FF 00FF 00FF E09B 862F
        00FF 82EF 8583 8180 8180 878F E09B 00FF 00FF 00FF 00FF 00FF 00FF 00FF E09B 824F
        00FF 83AF 83B0 83B2 83B0 87AF E09B 00FF 00FF 00FF 00FF 00FF 00FF 00FF E09B 828F
        00FF 00FF 2321 00FF 2321 00FF 00FF 00FF 00FF 00FF 00FF 00FF 00FF 00FF E09B 826F
      </Screen>
          <Screen X="3" Y="0">
        8180 8180 8180 8180 8180 8180 8180 8180 8180 8180 8180 8180 8180 8180 8180 8180
        83B1 83B1 83B0 83B1 83B0 83B0 83B0 83B3 8180 8180 8180 8180 8180 8180 8180 8180
        82EB 82EB 82EB 86EA E09B E09B E09B 838F 8980 8180 8180 8180 8180 8180 8180 8180
        00FF 00FF 00FF 00FF 00FF 00FF 00FF 83AF 8A26 8A29 8A2A 8BD3 8180 8180 8180 8180
        00FF 00FF 00FF 00FF 00FF 00FF 00FF 00FF 00FF 00FF 8CE4 824F 8180 8180 8180 8180
        00FF 00FF 00FF 00FF 00FF 00FF 00FF 00FF 82ED 86EC 00FF 82AF 8180 8180 8180 8180
        00FF 00FF 00FF 00FF 00FF 00FF 00FF 00FF E09B 834D 00FF 826F 8180 8180 8180 8180
        00FF 00FF 00FF 00FF 00FF 00FF 00FF 00FF E09B 836D 00FF 82CF 8180 8180 8180 8180
        00FF 00FF 00FF 00FF 00FF 00FF 00FF 00FF E09B 836D 00FF 82EF 8180 8180 8180 8180
        82E2 8363 8365 00FF 00FF 00FF 00FF 00FF E09B 838D 00FF 82EF 8180 8180 8180 8180
        8302 8383 8385 00FF 00FF 00FF 00FF 00FF E09B 832D 00FF 824F 8180 8180 8180 8180
        8321 80FF E09B 00FF 00FF 00FF 00FF 00FF E09B 834D 00FF 826F 8180 8180 8180 8180
        822B 822F E09B 00FF 00FF 00FF 00FF 00FF E09B 836D 00FF 828F 8180 8180 8180 8180
        8180 878F E09B 00FF 00FF 00FF 00FF 00FF E09B 838D 00FF 826F 8180 8180 8180 8180
        8180 8ECF E09B 00FF 00FF 00FF 00FF 00FF 8AED 8EEC 00FF 82AF 8180 8180 8180 8180
        8180 868F E09B 00FF 00FF 00FF 00FF 00FF 00FF 00FF 00FF 828F 8180 8180 8180 8180
      </Screen>
          <Screen X="0" Y="1">
        8180 8180 8180 86EF 00FF 00FF 00FF 00FF 00FF 00FF 00FF 00FF 00FF 00FF 00FF 00FF
        8180 85A3 8180 870F 00FF 00FF 00FF 00FF 00FF 00FF 00FF 00FF 00FF 00FF 00FF 00FF
        8180 85A3 8180 872F 00FF 00FF 00FF 00FF 00FF 00FF 00FF 00FF 00FF 00FF 00FF 00FF
        8180 8180 8180 874F 00FF 00FF 00FF 00FF 00FF 00FF 00FF 00FF 00FF 00FF 00FF 00FF
        8180 85A3 8180 86EF 00FF 00FF 00FF 00FF 00FF 00FF 00FF 00FF 00FF 00FF 00FF 00FF
        8180 8180 8180 86EF 00FF 00FF 00FF 00FF 00FF 00FF 00FF 00FF 00FF 00FF 00FF 00FF
        8180 8180 8180 876F 82E2 82E2 82E0 82E2 82E2 82E2 82E0 82E2 82E2 82E2 82E0 12E2
        8180 8180 8180 878F 8302 8302 8300 8302 8381 8302 8300 8302 8302 8302 8300 8382
        85A0 8180 8180 86EF 80FF 80FF 8320 80FF 80FF 80FF 8322 80FF 80FF 80FF 8320 80FF
        85A1 8161 8180 87D3 822B 822B 822B 822B 822C 822D 822D 822D 822E 822B 822B 822B
        8182 8162 8161 8180 8180 8180 8180 8180 8180 8180 8180 8180 8180 8180 8180 8180
        8182 8182 85A1 8161 85A0 8180 81A3 8180 8180 8180 81A4 81A3 8180 81A4 8180 85A3
        8182 8182 8962 8181 8181 8180 8160 8180 8180 8180 8180 8180 8180 8180 8180 8180
        8182 8182 8181 8181 8181 81A1 8181 8161 8180 8180 81A0 85A0 8180 8180 8180 8180
        8182 8182 8182 8162 81A1 8182 8182 8162 8161 81A1 8162 8181 8161 8180 8180 8180
        8182 8182 8182 8182 8182 8182 8182 8182 8182 8182 8182 8162 8181 8180 8180 8180
      </Screen>
          <Screen X="1" Y="1">
        00FF 00FF 00FF 00FF 00FF 00FF 00FF 00FF 00FF 00FF 00FF 00FF 00FF 00FF 00FF 00FF
        00FF 00FF 00FF 00FF 00FF 00FF 00FF 00FF 00FF 00FF 00FF 00FF 00FF 00FF 00FF 00FF
        00FF 00FF 00FF 00FF 00FF 00FF 00FF 00FF 00FF 00FF 00FF 00FF 00FF 00FF 00FF 00FF
        00FF 00FF 00FF 00FF 00FF 00FF 00FF 00FF 00FF 00FF 00FF 00FF 00FF 00FF 00FF 00FF
        00FF 00FF 00FF 00FF 00FF 00FF 00FF 00FF 00FF 00FF 00FF 00FF 00FF 00FF 00FF 00FF
        00FF 00FF 00FF 00FF 00FF 00FF 00FF 00FF 00FF 00FF 00FF 00FF 00FF 00FF 00FF 00FF
        12E1 12E3 12E4 00FF 00FF 00FF 00FF 00FF 00FF 00FF 00FF 00FF 00FF 00FF 00FF 00FF
        8301 8303 8304 8363 E09B 00FF 00FF 00FF 00FF 00FF 00FF 00FF 00FF 00FF 00FF 00FF
        80FF 8323 8324 8383 E09B 00FF 00FF 00FF 00FF 00FF 00FF 00FF 00FF 00FF 00FF 00FF
        81C8 81C9 80FF 80FF E09B 00FF 00FF 00FF 00FF 00FF 00FF 00FF 00FF 00FF 00FF 00FF
        81E8 81E9 81C8 81C9 E09B 00FF 00FF 00FF 00FF 00FF 00FF 00FF 00FF 00FF 00FF 00FF
        8180 8180 81E8 81E9 E09B 00FF 00FF 00FF 00FF 00FF 00FF 00FF 00FF 00FF 00FF 00FF
        8180 8180 8180 8180 E09B 00FF 00FF 00FF 00FF 00FF 00FF 00FF 00FF 00FF 00FF 00FF
        8180 8180 8180 8180 E09B 00FF 00FF 00FF 00FF 00FF 00FF 00FF 00FF 00FF 00FF 00FF
        8180 8180 8180 81A0 E09B 00FF 00FF 00FF 00FF 00FF 00FF 00FF 00FF 00FF 00FF 00FF
        8180 81A0 8181 8181 E09B 00FF 00FF 00FF 00FF 00FF 00FF 00FF 00FF 00FF 00FF 00FF
      </Screen>
          <Screen X="2" Y="1">
        00FF 00FF 2320 00FF 2320 00FF 00FF 00FF 00FF 00FF 00FF 00FF 00FF 00FF E09B 82CF
        00FF E09B E09B E09B E09B E09B 00FF 00FF 00FF 00FF 00FF 00FF 00FF 00FF E09B 838F
        00FF 00FF 00FF 00FF 00FF 00FF 00FF 00FF 00FF 00FF 00FF 00FF 00FF 00FF E09B 824F
        00FF 00FF 00FF 00FF 00FF 00FF 00FF 00FF 00FF 00FF 00FF 00FF 00FF 00FF E09B 826F
        00FF 00FF 00FF 00FF 00FF 00FF 00FF 00FF 00FF 00FF 00FF 00FF 00FF 00FF E09B 828F
        00FF 00FF 00FF 00FF 00FF 00FF 00FF 00FF 04FF 00FF 00FF 00FF 00FF 00FF E09B 826F
        00FF 00FF 00FF 00FF 00FF 00FF 00FF 00FF 00FF 00FF 00FF 00FF 00FF 00FF E09B 828F
        00FF 00FF 00FF 00FF 00FF 00FF 00FF 00FF 00FF 00FF 00FF 00FF 00FF 00FF E09B 826F
        00FF 00FF 00FF 00FF 00FF 00FF 00FF 00FF 00FF 00FF 00FF 00FF 00FF 00FF E09B 82CF
        00FF 00FF 00FF 00FF 00FF 00FF 00FF 00FF 00FF 00FF 00FF 00FF 00FF 00FF 862F 83D3
        00FF 00FF 00FF 00FF 00FF 00FF 00FF 00FF 00FF 00FF 00FF 00FF 00FF 00FF 82EF 8180
        00FF 00FF 00FF 00FF 00FF 00FF 00FF 00FF 00FF 00FF 00FF 00FF 00FF 00FF 82EF 8180
        00FF 00FF 00FF 00FF 00FF 00FF 00FF 00FF 00FF 00FF 00FF 00FF 00FF 00FF 82EF 8180
        00FF 00FF 00FF 00FF 00FF 00FF 00FF 00FF 00FF 00FF 00FF 00FF 00FF 00FF 82EF 8180
        00FF 00FF 00FF 00FF 00FF 00FF 00FF 00FF 00FF 00FF 00FF 00FF 00FF 00FF 82EF 8180
        00FF 00FF 00FF 00FF 00FF 00FF 00FF 00FF 00FF 00FF 00FF 00FF 00FF 00FF 82EF 8180
      </Screen>
          <Screen X="3" Y="1">
        8180 866F E09B 00FF 00FF 00FF 00FF 00FF 00FF 00FF 00FF 826F 8180 8180 8180 8180
        8180 868F E09B 00FF 00FF 00FF 00FF 00FF 00FF 00FF 00FF 82CF 8161 8180 8183 8180
        8180 86CF E09B 00FF 00FF 00FF 00FF 00FF 00FF 00FF 00FF 82EF 8162 8161 8180 8180
        8180 838F E09B 00FF 00FF 00FF 00FF 00FF 00FF 00FF 00FF 8E2F 8A26 8A27 8A27 8A27
        8180 838F E09B 00FF 00FF 00FF 00FF 00FF 00FF 00FF 80E4 00FF 00FF 00FF 00FF 00FF
        8180 838F 818C 00FF 00FF 00FF 818C 82EA 82EB 86EA 818C 82EA 82EB 86EA 818C 82EA
        8180 864F 834D 00FF 00FF 00FF 00FF 00FF 00FF 00FF 00FF 00FF 00FF 00FF C00C 9040
        8180 866F 836D 00FF 00FF 00FF 00FF 00FF 00FF 00FF 00FF 00FF 00FF 00FF D02C 9060
        8180 868F 838D 00FF 00FF 00FF 00FF 00FF 00FF 00FF 00FF 00FF 00FF 00FF D82C 9860
        8180 86CF 83CD 00FF 00FF 00FF 00FF 00FF 00FF 00FF 00FF 00FF 00FF 00FF D80C 9840
        8180 87D3 822F 00FF 00FF 862F 822C 822D 822E 822F 00FF 00FF 862F 8226 8227 8228
        8180 8180 87D3 822B 822B 83D3 8180 8180 8180 87D3 822B 822B 83D3 81C5 81C0 81C2
        8180 8180 8183 8180 8180 81A3 81C0 81C2 81C5 8180 81C5 83AD 81E4 81E5 8200 8202
        8180 8180 8180 81C0 81C2 8180 8200 8202 8184 8180 81C0 81C1 81C1 81C2 81A4 8180
        8180 8180 8180 81E0 81E2 8180 8180 8183 8180 8183 8200 8201 8201 8202 8180 8184
        81A3 8180 8180 8200 8202 8180 8180 8180 8180 8180 8180 8180 8180 8180 8180 8180
      </Screen>
          <Screen X="0" Y="2">
        8182 8182 8182 8182 8182 8182 8182 8182 8182 8182 8182 8962 8181 8180 8180 8180
        8182 8182 8182 8182 8182 8182 8182 8182 8182 8182 8DA1 8181 8961 8180 8180 8180
        8182 8182 8182 8182 8182 8182 8182 8182 8182 8182 8181 8961 8180 8180 8180 8180
        8182 8182 8182 8182 8182 8182 8182 8182 8182 8182 8181 8180 8180 8180 8584 8180
        8182 8182 8182 8182 8182 8182 8182 8182 8182 8182 8181 8180 8180 8180 8180 8180
        8182 8182 8182 8182 8182 8182 8182 8182 8182 8182 8181 8180 8180 8180 8180 8180
        8182 8182 8182 8182 8182 8182 8182 8182 8182 8182 8162 8161 8180 8180 85A3 8180
        8182 8182 8182 8182 8182 8182 8182 8182 8182 8182 8182 8181 8161 8180 8180 8180
        8182 8182 8182 8182 8182 8182 8182 8182 8182 89A1 8962 8181 8181 8180 8180 8180
        8182 8182 8182 8182 8182 8182 8182 8182 8182 8181 8181 8181 8181 8180 8180 8180
        8182 8182 8182 8182 8182 8182 8182 8182 8962 8181 8181 8181 8181 8180 8180 8180
        8182 8182 8182 8182 8182 8182 8182 8181 8181 8181 8181 8181 8961 8180 8180 8180
        8182 8182 8182 8182 8182 8182 8182 8162 8181 8181 8181 8181 8180 8180 8180 8180
        8182 8182 8182 8182 8182 8182 8182 8182 8182 8162 8181 8181 8180 8180 8180 8180
        8182 8182 8182 8182 8182 8182 8182 8182 8182 8182 8181 8181 8161 8180 8180 8180
        8182 8182 8182 8182 8182 8182 8182 8182 8182 8182 8162 8181 8181 8181 8161 8180
      </Screen>
          <Screen X="1" Y="2">
        81A1 8186 8187 83B0 8A2F 00FF 00FF 00FF 00FF 00FF 00FF 00FF 00FF 00FF 00FF 00FF
        87B3 11A6 11A7 00FF 00FF 00FF 00FF 00FF 00FF 00FF 00FF 00FF 00FF 00FF 00FF 00FF
        86EF 00FF 00FF 00FF 00FF 00FF 00FF 00FF 00FF 00FF 00FF 00FF 00FF 00FF 00FF 00FF
        86EF 00FF 00FF 00FF 00FF 00FF 00FF 00FF 00FF 00FF 00FF 00FF 00FF 00FF 00FF 00FF
        86EF 00FF 00FF 00FF 00FF 00FF 00FF 00FF 00FF 00FF 00FF 00FF 00FF 00FF 00FF 00FF
        870F 00FF 00FF 00FF 00FF 00FF 00FF 00FF 00FF 00FF 00FF 00FF 00FF 00FF 00FF 00FF
        8F2F 00FF 00FF 00FF 00FF 8765 82E0 82E2 8360 82E2 82E0 8365 00FF 00FF 00FF 00FF
        8F2F 00FF 00FF 00FF 00FF 1785 8300 8380 8382 8380 8300 1385 00FF 00FF 00FF 00FF
        8F2F 00FF 00FF 00FF 00FF 00FF 2321 00FF 00FF 00FF 2321 00FF 00FF 00FF 00FF 00FF
        8F2F 00FF 00FF 00FF 00FF 00FF 2321 00FF 00FF 00FF 2321 00FF 00FF 00FF 00FF 00FF
        874F 00FF 00FF 00FF 00FF 00FF 2321 00FF 00FF 00FF 2321 00FF 00FF 00FF 00FF 00FF
        86EF 00FF 00FF 00FF 00FF 00FF 2321 00FF 00FF 00FF 2321 00FF 00FF 00FF 00FF 00FF
        86EF 00FF 00FF 00FF 00FF 00FF 2321 00FF 00FF 00FF 2321 00FF 00FF 00FF 00FF 00FF
        87D3 11C8 11C9 00FF 00FF 00FF 2320 00FF 00FF 00FF 2320 00FF 00FF 00FF 11C6 11C7
        8180 81E8 81E9 822B 822B 822B 822B 822B 822B 822B 822B 822B 822B 822B 81E6 85E8
        8180 8180 8180 8180 8180 8180 8180 8180 8180 8180 8180 8180 8180 8180 8180 8180
      </Screen>
          <Screen X="2" Y="2">
        00FF 00FF 00FF 00FF 00FF 00FF 00FF 00FF 00FF 00FF 00FF 00FF 00FF 00FF 82EF 8180
        00FF 00FF 00FF 00FF 00FF 00FF 00FF 00FF 00FF 00FF 00FF 00FF 00FF 00FF 830F 8180
        00FF 00FF 00FF 00FF 00FF 00FF 00FF 00FF 00FF 00FF 00FF 00FF 00FF 00FF 832F 8180
        00FF 00FF 00FF 00FF 00FF 00FF 00FF 00FF 00FF 00FF 00FF 00FF 00FF 00FF 834F 8180
        00FF 00FF 00FF 00FF 00FF 00FF 00FF 00FF 00FF 00FF 00FF 00FF 00FF 00FF 82EF 8180
        00FF 00FF 00FF 00FF 00FF 00FF 00FF 00FF 00FF 00FF 00FF 00FF 00FF 00FF 82EF 8180
        00FF 00FF 00FF 00FF 00FF 00FF 00FF 00FF 00FF 00FF 00FF 00FF 00FF 00FF 82EF 8180
        00FF 00FF 00FF 00FF 00FF 00FF 00FF 00FF 00FF 00FF 00FF 00FF 00FF 00FF 82EF 8180
        00FF 00FF 00FF 00FF 00FF 00FF 00FF 00FF 00FF 00FF 00FF 00FF 00FF 11CA 81CB 8180
        00FF 00FF 00FF 00FF 00FF 00FF 00FF 00FF 00FF 00FF 00FF 00FF 00FF 11EA 81EB 8180
        00FF 00FF 00FF 00FF 00FF 00FF 00FF 00FF 00FF 00FF 00FF 00FF 11CA 11CB 8180 81A3
        00FF 00FF 00FF 00FF 00FF 00FF 00FF 00FF 00FF 00FF 00FF 00FF 11EA 11EB 8180 8180
        00FF 00FF 00FF 00FF 00FF 00FF 00FF 00FF 00FF 00FF 11C6 11C7 13D3 1180 8180 8180
        122B 122B 862E 862D 862D 862D 862C 822B 822B 822B 81E6 85E8 8180 8180 8180 8180
        8180 8180 8180 8180 8180 8180 8180 8180 8180 8180 8180 8180 8180 8180 8180 8180
        8180 8180 8180 8180 8180 8180 8180 8180 8180 8180 8180 8180 8180 8180 8180 8180
      </Screen>
          <Screen X="3" Y="2">
        8180 8180 8180 8180 8180 8180 8180 81A4 8180 8180 8180 8180 8180 8180 8180 8180
        8184 8180 8180 8180 8180 8180 8180 8180 8180 8180 8180 8180 8180 8180 8180 8180
        8180 8180 8180 8180 8180 8180 8180 8180 8180 8180 8180 8180 8180 8180 8180 8180
        8180 8180 8180 8180 8180 8180 8180 8180 8180 8180 8180 8180 8180 8180 8180 8180
        81A3 8180 8180 8180 8180 8180 8180 8180 8180 8180 8180 8180 8180 8180 8180 8180
        8180 8180 8180 8180 8180 8180 8180 8180 8180 8180 8180 8180 8180 8180 8180 8180
        8180 8180 8180 8180 8180 8180 8180 8180 8180 8180 8180 8180 8180 8180 8180 8180
        8180 8180 8180 8180 8180 8180 8180 8180 8180 8180 8180 8180 8180 8180 8180 8180
        8180 8180 8180 8180 8180 8180 8180 8180 8180 8180 8180 8180 8180 8180 8180 8180
        8180 8180 8180 8180 8180 8180 8180 8180 8180 8180 8180 8180 8180 8180 8180 8180
        8180 8180 8180 8180 8180 8180 8180 8180 8180 8180 8180 8180 8180 8180 8180 8180
        8180 8180 8180 8180 8180 8180 8180 8180 8180 8180 8180 8180 8180 8180 8180 8180
        8180 8180 8180 8180 8180 8180 8180 8180 8180 8180 8180 8180 8180 8180 8180 8180
        8180 8180 8180 8180 8180 8180 8180 8180 8180 8180 8180 8180 8180 8180 8180 8180
        8180 8180 8180 8180 8180 8180 8180 8180 8180 8180 8180 8180 8180 8180 8180 8180
        8180 8180 8180 8180 8180 8180 8180 8180 8180 8180 8180 8180 8180 8180 8180 8180
      </Screen>
        </Layer1>
        <BTS>
          <Screen X="0" Y="0">
        00 00 00 00 00 00 00 00 00 00 00 00 00 00 00 00
        00 00 00 00 00 00 00 00 00 00 00 00 00 00 00 00
        00 00 00 00 00 00 00 00 00 00 00 00 00 00 00 00
        00 00 00 00 00 00 00 00 00 00 00 00 00 00 00 00
        00 00 00 D3 D3 D7 D6 00 00 00 00 00 96 97 00 00
        00 00 93 D7 D6 00 00 00 00 00 00 00 00 00 00 00
        00 41 00 00 00 00 00 00 00 00 00 00 00 00 00 00
        00 FF 00 00 00 00 00 00 00 00 00 00 00 00 00 00
        00 FE 00 00 00 00 00 00 00 00 00 00 00 00 00 00
        00 FD 00 00 00 00 00 00 00 00 00 00 00 00 00 00
        00 00 00 00 00 00 00 00 00 00 00 00 00 00 00 00
        00 00 00 00 00 00 00 DC 00 00 00 00 00 00 00 00
        00 00 00 00 D7 D6 00 00 00 00 00 00 00 00 00 00
        00 00 00 00 00 00 00 00 00 00 00 00 00 00 00 00
        00 00 00 00 00 00 00 00 00 00 00 00 00 00 00 00
        00 00 00 00 00 00 00 00 00 00 00 00 00 00 00 00
      </Screen>
          <Screen X="1" Y="0">
        00 00 00 00 00 00 00 00 00 00 00 00 00 00 00 00
        00 00 00 00 00 00 00 00 00 00 00 00 00 00 00 00
        00 00 00 00 00 00 00 00 00 00 00 00 00 00 00 00
        00 00 00 00 00 00 00 00 00 00 00 00 00 00 00 00
        00 00 00 00 00 00 00 00 00 00 00 00 00 00 00 00
        00 00 00 00 00 00 00 00 00 00 00 00 00 00 00 00
        00 00 00 00 00 00 00 00 00 00 00 00 00 00 00 00
        00 00 96 97 93 93 00 00 00 00 00 00 00 00 00 00
        00 00 00 00 96 97 00 00 00 00 00 00 00 00 00 00
        00 00 00 00 00 00 00 00 00 00 00 00 00 00 00 00
        00 00 00 00 00 00 00 00 00 00 00 00 00 96 97 93
        00 00 00 00 00 00 00 00 00 00 00 00 00 00 00 96
        00 00 00 00 00 00 00 00 00 00 00 00 00 00 00 00
        00 00 00 00 00 00 00 00 00 00 00 00 00 00 00 00
        00 00 00 00 00 00 00 00 00 00 00 00 00 00 00 00
        00 00 00 00 00 00 00 00 00 00 00 00 00 00 00 00
      </Screen>
          <Screen X="2" Y="0">
        00 00 00 00 00 00 00 00 00 00 00 00 00 00 00 00
        00 00 00 00 00 00 00 00 00 00 00 00 00 00 00 00
        00 00 00 00 00 00 00 00 00 00 00 00 00 00 00 00
        00 00 00 00 00 00 00 00 00 00 00 00 00 00 00 00
        00 00 00 00 00 00 00 00 00 00 00 00 00 00 00 00
        00 00 00 00 00 00 00 00 00 00 00 00 00 00 00 00
        00 00 00 00 00 00 00 00 00 00 00 00 00 00 00 00
        00 00 00 00 00 00 00 00 00 00 00 00 00 00 00 00
        00 00 00 00 00 00 00 00 00 00 00 00 00 00 00 00
        00 00 00 00 00 00 00 00 00 00 00 00 00 00 00 00
        93 00 00 00 00 00 00 00 00 00 00 00 00 00 00 00
        97 00 00 00 00 00 00 00 00 00 00 00 00 00 00 00
        00 00 00 00 00 00 00 00 00 00 00 00 00 00 00 00
        00 00 00 00 00 00 00 00 00 00 00 00 00 00 00 00
        00 00 00 00 00 00 00 00 00 00 00 00 00 00 00 00
        00 00 00 00 00 00 00 00 00 00 00 00 00 00 00 00
      </Screen>
          <Screen X="3" Y="0">
        00 00 00 00 00 00 00 00 00 00 00 00 00 00 00 00
        00 00 00 00 00 00 00 00 00 00 00 00 00 00 00 00
        00 00 00 00 00 00 00 00 00 00 00 00 00 00 00 00
        00 00 00 00 00 00 00 00 00 00 00 00 00 00 00 00
        00 00 00 00 00 00 00 00 00 00 00 00 00 00 00 00
        00 00 00 00 00 00 00 00 00 00 00 00 00 00 00 00
        00 00 00 00 00 00 00 00 00 00 00 00 00 00 00 00
        00 00 00 00 00 00 00 00 00 00 00 00 00 00 00 00
        00 00 00 00 00 00 00 00 00 00 00 00 00 00 00 00
        00 00 00 00 00 00 00 00 00 00 00 00 00 00 00 00
        00 00 00 00 00 00 00 00 00 00 00 00 00 00 00 00
        00 00 00 00 00 00 00 00 00 00 00 00 00 00 00 00
        00 00 00 00 00 00 00 00 00 00 00 00 00 00 00 00
        00 00 00 00 00 00 00 00 00 00 00 00 00 00 00 00
        00 00 00 00 00 00 00 00 00 00 00 00 00 00 00 00
        00 00 00 00 00 00 00 00 00 00 00 00 00 00 00 00
      </Screen>
          <Screen X="0" Y="1">
        00 00 00 00 00 00 00 00 00 00 00 00 00 00 00 00
        00 00 00 00 00 00 00 00 00 00 00 00 00 00 00 00
        00 00 00 00 00 00 00 00 00 00 00 00 00 00 00 00
        00 00 00 00 00 00 00 00 00 00 00 00 00 00 00 00
        00 00 00 00 00 00 00 00 00 00 00 00 00 00 00 00
        00 00 00 00 00 00 00 00 00 00 00 00 00 00 00 00
        00 00 00 00 00 00 00 00 00 00 00 00 00 00 00 13
        00 00 00 00 00 00 00 00 00 00 00 00 00 00 00 00
        00 00 00 00 00 00 00 00 00 00 00 00 00 00 00 00
        00 00 00 00 00 00 00 00 00 00 00 00 00 00 00 00
        00 00 00 00 00 00 00 00 00 00 00 00 00 00 00 00
        00 00 00 00 00 00 00 00 00 00 00 00 00 00 00 00
        00 00 00 00 00 00 00 00 00 00 00 00 00 00 00 00
        00 00 00 00 00 00 00 00 00 00 00 00 00 00 00 00
        00 00 00 00 00 00 00 00 00 00 00 00 00 00 00 00
        00 00 00 00 00 00 00 00 00 00 00 00 00 00 00 00
      </Screen>
          <Screen X="1" Y="1">
        00 00 00 00 00 00 00 00 00 00 00 00 00 00 00 00
        00 00 00 00 00 00 00 00 00 00 00 00 00 00 00 00
        00 00 00 00 00 00 00 00 00 00 00 00 00 00 00 00
        00 00 00 00 00 00 00 00 00 00 00 00 00 00 00 00
        00 00 00 00 00 00 00 00 00 00 00 00 00 00 00 00
        00 00 00 00 00 00 00 00 00 00 00 00 00 00 00 00
        13 57 56 00 00 00 00 00 00 00 00 00 00 00 00 00
        00 00 00 00 00 00 00 00 00 00 00 00 00 00 00 00
        00 00 00 00 00 00 00 00 00 00 00 00 00 00 00 00
        00 00 00 00 00 00 00 00 00 00 00 00 00 00 00 00
        00 00 00 00 00 00 00 00 00 00 00 00 00 00 00 00
        00 00 00 00 00 00 00 00 00 00 00 00 00 00 00 00
        00 00 00 00 00 00 00 00 00 00 00 00 00 00 00 00
        00 00 00 00 00 00 00 00 00 00 00 00 00 00 00 00
        00 00 00 00 00 00 00 00 00 00 00 00 00 00 00 00
        00 00 00 00 00 00 00 00 00 00 00 00 00 00 00 00
      </Screen>
          <Screen X="2" Y="1">
        00 00 00 00 00 00 00 00 00 00 00 00 00 00 00 00
        00 00 00 00 00 00 00 00 00 00 00 00 00 00 00 00
        00 00 00 00 00 00 00 00 00 00 00 00 00 00 00 00
        00 00 00 00 00 00 00 00 00 00 00 00 00 00 00 00
        00 00 00 00 00 00 00 00 00 00 00 00 00 00 00 00
        00 00 00 00 00 00 00 00 00 00 00 00 00 00 00 00
        00 00 00 00 00 00 00 00 00 00 00 00 00 00 00 00
        00 00 00 00 00 00 00 00 00 00 00 00 00 00 00 00
        00 00 00 00 00 00 00 00 00 00 00 00 00 00 00 00
        00 00 00 00 00 00 00 00 00 00 00 00 00 00 00 00
        00 00 00 00 00 00 00 00 00 00 00 00 00 00 00 00
        00 00 00 00 00 00 00 00 00 00 00 00 00 00 00 00
        00 00 00 00 00 00 00 00 00 00 00 00 00 00 00 00
        00 00 00 00 00 00 00 00 00 00 00 00 00 00 00 00
        00 00 00 00 00 00 00 00 00 00 00 00 00 00 00 00
        00 00 00 00 00 00 00 00 00 00 00 00 00 00 00 00
      </Screen>
          <Screen X="3" Y="1">
        00 00 00 00 00 00 00 00 00 00 00 00 00 00 00 00
        00 00 00 00 00 00 00 00 00 00 00 00 00 00 00 00
        00 00 00 00 00 00 00 00 00 00 00 00 00 00 00 00
        00 00 00 00 00 00 00 00 00 00 00 00 00 00 00 00
        00 00 00 00 00 00 00 00 00 00 00 00 00 00 00 00
        00 00 00 00 00 00 00 00 00 00 00 00 00 00 00 00
        00 00 00 00 00 00 00 00 00 00 00 00 00 00 40 01
        00 00 00 00 00 00 00 00 00 00 00 00 00 00 FF 01
        00 00 00 00 00 00 00 00 00 00 00 00 00 00 FE 01
        00 00 00 00 00 00 00 00 00 00 00 00 00 00 FD 01
        00 00 00 00 00 00 00 00 00 00 00 00 00 00 00 00
        00 00 00 00 00 00 00 00 00 00 00 00 00 00 00 00
        00 00 00 00 00 00 00 00 00 00 00 00 00 00 00 00
        00 00 00 00 00 00 00 00 00 00 00 00 00 00 00 00
        00 00 00 00 00 00 00 00 00 00 00 00 00 00 00 00
        00 00 00 00 00 00 00 00 00 00 00 00 00 00 00 00
      </Screen>
          <Screen X="0" Y="2">
        00 00 00 00 00 00 00 00 00 00 00 00 00 00 00 00
        00 00 00 00 00 00 00 00 00 00 00 00 00 00 00 00
        00 00 00 00 00 00 00 00 00 00 00 00 00 00 00 00
        00 00 00 00 00 00 00 00 00 00 00 00 00 00 00 00
        00 00 00 00 00 00 00 00 00 00 00 00 00 00 00 00
        00 00 00 00 00 00 00 00 00 00 00 00 00 00 00 00
        00 00 00 00 00 00 00 00 00 00 00 00 00 00 00 00
        00 00 00 00 00 00 00 00 00 00 00 00 00 00 00 00
        00 00 00 00 00 00 00 00 00 00 00 00 00 00 00 00
        00 00 00 00 00 00 00 00 00 00 00 00 00 00 00 00
        00 00 00 00 00 00 00 00 00 00 00 00 00 00 00 00
        00 00 00 00 00 00 00 00 00 00 00 00 00 00 00 00
        00 00 00 00 00 00 00 00 00 00 00 00 00 00 00 00
        00 00 00 00 00 00 00 00 00 00 00 00 00 00 00 00
        00 00 00 00 00 00 00 00 00 00 00 00 00 00 00 00
        00 00 00 00 00 00 00 00 00 00 00 00 00 00 00 00
      </Screen>
          <Screen X="1" Y="2">
        00 00 00 00 00 00 00 00 00 00 00 00 00 00 00 00
        00 D7 D6 00 00 00 00 00 00 00 00 00 00 00 00 00
        00 00 00 00 00 00 00 00 00 00 00 00 00 00 00 00
        00 00 00 00 00 00 00 00 00 00 00 00 00 00 00 00
        00 00 00 00 00 00 00 00 00 00 00 00 00 00 00 00
        00 00 00 00 00 00 00 00 00 00 00 00 00 00 00 00
        00 00 00 00 00 00 00 00 00 00 00 00 00 00 00 00
        00 00 00 00 00 9C 00 00 00 00 00 DC 00 00 00 00
        00 00 00 00 00 00 00 00 00 00 00 00 00 00 00 00
        00 00 00 00 00 00 00 00 00 00 00 00 00 00 00 00
        00 00 00 00 00 00 00 00 00 00 00 00 00 00 00 00
        00 00 00 00 00 00 00 00 00 00 00 00 00 00 00 00
        00 00 00 00 00 00 00 00 00 00 00 00 00 00 00 00
        00 57 56 00 00 00 00 00 00 00 00 00 00 00 16 17
        00 00 00 00 00 00 00 00 00 00 00 00 00 00 00 00
        00 00 00 00 00 00 00 00 00 00 00 00 00 00 00 00
      </Screen>
          <Screen X="2" Y="2">
        00 00 00 00 00 00 00 00 00 00 00 00 00 00 00 00
        00 00 00 00 00 00 00 00 00 00 00 00 00 00 00 00
        00 00 00 00 00 00 00 00 00 00 00 00 00 00 00 00
        00 00 00 00 00 00 00 00 00 00 00 00 00 00 00 00
        00 00 00 00 00 00 00 00 00 00 00 00 00 00 00 00
        00 00 00 00 00 00 00 00 00 00 00 00 00 00 00 00
        00 00 00 00 00 00 00 00 00 00 00 00 00 00 00 00
        00 00 00 00 00 00 00 00 00 00 00 00 00 00 00 00
        00 00 00 00 00 00 00 00 00 00 00 00 00 1B 00 00
        00 00 00 00 00 00 00 00 00 00 00 00 00 1C 00 00
        00 00 00 00 00 00 00 00 00 00 00 00 1B 13 00 00
        00 00 00 00 00 00 00 00 00 00 00 00 1C 13 00 00
        00 00 00 00 00 00 00 00 00 00 16 17 13 13 00 00
        13 13 00 00 00 00 00 00 00 00 00 00 00 00 00 00
        00 00 00 00 00 00 00 00 00 00 00 00 00 00 00 00
        00 00 00 00 00 00 00 00 00 00 00 00 00 00 00 00
      </Screen>
          <Screen X="3" Y="2">
        00 00 00 00 00 00 00 00 00 00 00 00 00 00 00 00
        00 00 00 00 00 00 00 00 00 00 00 00 00 00 00 00
        00 00 00 00 00 00 00 00 00 00 00 00 00 00 00 00
        00 00 00 00 00 00 00 00 00 00 00 00 00 00 00 00
        00 00 00 00 00 00 00 00 00 00 00 00 00 00 00 00
        00 00 00 00 00 00 00 00 00 00 00 00 00 00 00 00
        00 00 00 00 00 00 00 00 00 00 00 00 00 00 00 00
        00 00 00 00 00 00 00 00 00 00 00 00 00 00 00 00
        00 00 00 00 00 00 00 00 00 00 00 00 00 00 00 00
        00 00 00 00 00 00 00 00 00 00 00 00 00 00 00 00
        00 00 00 00 00 00 00 00 00 00 00 00 00 00 00 00
        00 00 00 00 00 00 00 00 00 00 00 00 00 00 00 00
        00 00 00 00 00 00 00 00 00 00 00 00 00 00 00 00
        00 00 00 00 00 00 00 00 00 00 00 00 00 00 00 00
        00 00 00 00 00 00 00 00 00 00 00 00 00 00 00 00
        00 00 00 00 00 00 00 00 00 00 00 00 00 00 00 00
      </Screen>
        </BTS>
        <Layer2>
          <Screen X="0" Y="0">
        00FF 00FF 00FF 00FF 00FF 00FF 00FF 00FF 00FF 00FF 00FF 00FF 00FF 00FF 00FF 00FF
        00FF 00FF 00FF 00FF 00FF 00FF 00FF 00FF 00FF 00FF 00FF 00FF 00FF 00FF 00FF 00FF
        00FF 00FF 00FF 00FF 00FF 00FF 00FF 0267 00FF 00FF 00FF 00FF 00FF 00FF 00FF 00FF
        00FF 00FF 00FF 00FF 00FF 02A2 0265 0267 0243 0643 0268 0281 0243 0643 00FF 00FF
        0246 0246 0246 0246 0247 02A2 0265 0267 0243 0643 0268 02A1 0243 0643 0268 00FF
        0266 0266 0266 02A6 0267 02A2 0265 0267 0243 0643 0268 0281 0243 0643 0268 0281
        0266 0266 0266 0266 0267 02A2 0285 0287 0243 0643 0268 0281 0243 0643 0268 0281
        0266 02A6 0266 0266 0267 02A2 0268 06A4 0243 0643 02A3 0281 0263 0663 0268 0281
        0266 0266 0266 0266 0267 02A2 0268 02A2 0263 0663 0268 0281 0243 0643 0268 0281
        0266 0266 02A9 02A9 0267 02A2 0268 02A2 0243 0643 0268 0281 0243 0643 0268 0281
        0266 0266 0266 0266 0267 02A2 0268 02A2 0243 0643 0268 0281 0243 0643 0268 0281
        0286 0286 0286 0286 0287 02A2 0268 02A2 0243 0643 0268 02A1 0243 0643 0268 0281
        00FF 02A3 02A3 02A3 02A3 02A2 02A3 0684 0243 0643 0268 0281 0243 0643 0268 0281
        00FF 00FF 0268 0268 0268 0284 02A3 02A3 0243 0643 02A3 02A3 02A3 02A3 02A3 02A3
        00FF 00FF 00FF 0245 0246 0246 0246 0247 0243 0643 0268 0281 0243 0643 0268 0281
        00FF 00FF 00FF 0265 0266 0266 0266 0267 0243 064B 0241 0241 0241 0241 0241 0241
      </Screen>
          <Screen X="1" Y="0">
        00FF 00FF 00FF 00FF 00FF 00FF 00FF 00FF 00FF 00FF 00FF 00FF 00FF 00FF 02A2 00FF
        00FF 00FF 00FF 00FF 00FF 00FF 00FF 00FF 00FF 00FF 00FF 00FF 00FF 00FF 02A2 0268
        00FF 00FF 00FF 00FF 00FF 00FF 00FF 00FF 00FF 00FF 00FF 00FF 00FF 00FF 02A2 0268
        00FF 00FF 00FF 00FF 00FF 00FF 00FF 00FF 00FF 00FF 00FF 00FF 00FF 00FF 02A2 0268
        00FF 00FF 00FF 00FF 00FF 00FF 00FF 00FF 00FF 00FF 00FF 00FF 00FF 00FF 0284 02A3
        0281 0243 0643 00FF 00FF 00FF 00FF 00FF 00FF 00FF 00FF 00FF 00FF 00FF 0268 0268
        0281 0243 0643 0281 0243 0643 02A2 0243 0643 0268 0243 0643 0265 0266 0266 0267
        0281 0243 0643 0281 0243 0643 02A2 0243 0643 0268 0243 0643 0265 0266 0266 0267
        0281 0243 0643 0281 0243 0643 02A2 0243 0643 0268 0243 0643 0265 0266 0266 0267
        0281 0244 0644 0281 0243 0643 02A2 0243 0643 0268 0243 0643 0265 0266 0266 0267
        0281 0243 0643 0281 0243 0643 02A2 0243 0643 0268 0243 0643 0265 0266 0266 0267
        0281 0269 0669 0281 0243 0643 02A2 0243 0643 0268 0243 0643 0285 0286 0286 0287
        0281 0289 0689 0281 0243 0643 0284 0243 0643 02A3 0243 0643 02A3 02A3 02A3 02A3
        02A3 02A3 02A3 02A3 0243 0643 02A3 0243 0643 02A3 0243 0643 02A4 0268 0268 0268
        0281 0268 0268 0281 0263 0663 0268 0243 0643 0268 0243 0643 02A2 0245 0246 0247
        0241 028B 028C 0281 0244 0644 0268 0243 0643 0268 0269 0669 02A2 0265 0266 0267
      </Screen>
          <Screen X="2" Y="0">
        00FF 00FF 00FF 00FF 00FF 00FF 00FF 00FF 00FF 0243 0643 00FF 00FF 00FF 00FF 00FF
        0268 0268 0268 0268 0268 0268 0265 0266 0267 0243 0643 0265 0267 02A2 0268 02A2
        0268 0268 0268 0268 0268 0268 0265 0266 0267 0243 0643 0265 0267 02A2 0268 02A2
        0268 0268 0268 0268 0268 0268 0285 0286 0287 0243 0643 0285 0287 02A2 0268 02A2
        02A3 02A3 02A3 02A3 02A3 02A3 02A3 02A3 02A3 02A3 02A3 02A3 02A3 02A3 02A3 02A3
        0268 0268 0268 0268 0268 0268 0268 0268 0268 0243 0643 0268 0268 02A2 0268 02A2
        0281 0268 0281 0268 0268 02A3 02A3 02A3 02A3 02A3 02A3 02A3 02A3 02A3 02A3 0684
        0281 0268 0281 0268 0268 0246 0246 0246 0247 0243 0643 0245 0247 02A2 0245 0246
        0281 0268 0281 0268 0268 0266 0266 0266 0267 0263 0663 0265 0267 02A2 0265 0266
        0281 0268 0281 0268 0268 0286 0286 0286 0287 0243 0643 0285 0287 02A2 0265 0266
        0281 0268 0281 0268 0268 02A3 02A3 02A3 02A3 0243 0643 02A3 02A3 0684 0285 0286
        0281 0268 0281 0268 0268 0268 0268 0268 0268 0243 0643 0268 0268 0268 0268 0268
        0281 02A3 02A3 02A3 02A3 02A3 02A3 02A3 02A3 0243 0643 02A3 02A3 02A3 02A3 02A3
        0281 0268 0281 0245 0246 0246 0246 0246 0247 0243 0643 0268 0268 0268 0268 0268
        0281 0268 0281 0265 0266 0266 0266 0266 0267 0243 0643 0268 068C 068B 0241 0241
        0281 0268 02A1 0265 0266 02A9 0266 0266 0267 0243 0643 0268 06AC 06AB 0261 0261
      </Screen>
          <Screen X="3" Y="0">
        00FF 00FF 00FF 00FF 00FF 00FF 00FF 00FF 00FF 00FF 00FF 00FF 00FF 00FF 00FF 00FF
        0265 0266 0267 0243 0643 0281 0281 0268 0268 0268 0268 00FF 00FF 00FF 00FF 00FF
        0265 0266 0267 0243 0643 0281 0281 0268 0268 0268 0268 00FF 00FF 00FF 00FF 00FF
        0285 0286 0287 0243 0643 0281 0281 0268 0268 0268 0268 00FF 00FF 00FF 00FF 00FF
        02A3 02A3 02A3 02A3 02A3 02A3 02A3 02A3 02A3 02A3 02A4 00FF 00FF 00FF 00FF 00FF
        0245 0246 0247 0243 0643 0281 0281 0268 0268 0268 02A2 00FF 00FF 00FF 00FF 00FF
        0265 0266 0267 0243 0643 0281 02A1 0268 0268 0268 02A2 00FF 00FF 00FF 00FF 00FF
        0288 0266 0267 0263 0663 0281 0281 0268 0268 0268 02A2 00FF 00FF 00FF 00FF 00FF
        0266 0266 0267 0243 0643 0281 0281 0268 0268 0268 02A2 00FF 00FF 00FF 00FF 00FF
        0266 0266 0267 0243 0643 0281 0281 0268 0268 0268 02A2 00FF 00FF 00FF 00FF 00FF
        0286 0286 0287 0243 0643 02A1 0281 0268 0268 0268 02A2 00FF 00FF 00FF 00FF 00FF
        0268 0268 0268 0243 0643 0281 0281 0268 0268 0268 02A2 00FF 00FF 00FF 00FF 00FF
        02A3 02A3 02A3 0243 0643 0281 02A1 02A3 02A3 02A3 02A2 02A3 02A3 02A3 00FF 00FF
        0268 0268 0268 0243 0643 0281 0281 0268 0268 0268 02A2 0268 0268 0268 00FF 00FF
        0241 0241 0241 0241 0241 0281 0281 0241 0241 0241 02A2 0241 0241 0241 00FF 00FF
        0261 0261 0261 0261 0261 0281 0281 0261 0261 0261 02A2 0261 0261 0261 00FF 00FF
      </Screen>
          <Screen X="0" Y="1">
        00FF 00FF 00FF 0265 0266 0266 02A8 0267 066C 066B 0261 0261 0261 0261 0261 0261
        00FF 00FF 00FF 0265 0266 0266 0266 0688 0246 0246 0247 0281 0243 0643 0268 0281
        00FF 00FF 00FF 0265 0266 0266 0266 02A9 02A9 0266 0267 0281 0263 0663 0268 0281
        00FF 00FF 00FF 0265 0266 02A6 0266 0266 0266 0266 0267 0281 0243 0643 0268 0281
        00FF 00FF 00FF 0285 0286 0286 0286 0286 0286 0286 0287 02A1 0243 0643 0268 0281
        00FF 00FF 00FF 02A3 02A3 02A3 02A3 02A3 02A3 02A3 02A3 0281 0243 0643 02A3 02A3
        00FF 00FF 00FF 0246 0246 0246 0246 0247 0245 0246 0247 0281 0243 0643 0268 0281
        00FF 00FF 00FF 0266 0266 0266 0266 0267 0265 0266 0267 0281 0243 0643 0268 0281
        00FF 00FF 00FF 0286 0286 0286 0286 0287 0285 0286 0287 0281 0243 0643 0268 0281
        00FF 02A3 02A3 02A3 02A3 02A3 02A3 02A3 02A3 02A3 02A3 02A3 0243 0643 02A3 0281
        00FF 00FF 00FF 00FF 00FF 00FF 00FF 00FF 00FF 00FF 00FF 0281 0243 0643 00FF 0281
        00FF 00FF 00FF 00FF 00FF 00FF 00FF 00FF 00FF 00FF 00FF 0281 00FF 00FF 00FF 00FF
        00FF 00FF 00FF 00FF 00FF 00FF 00FF 00FF 00FF 00FF 00FF 0281 00FF 00FF 00FF 00FF
        00FF 00FF 00FF 00FF 00FF 00FF 00FF 00FF 00FF 00FF 00FF 0281 00FF 00FF 00FF 02A3
        00FF 00FF 00FF 00FF 00FF 00FF 00FF 00FF 00FF 00FF 00FF 0281 00FF 00FF 00FF 00FF
        00FF 00FF 00FF 00FF 00FF 00FF 00FF 00FF 00FF 00FF 00FF 0281 00FF 00FF 00FF 00FF
      </Screen>
          <Screen X="1" Y="1">
        0261 02AB 02AC 0281 0243 0643 0268 0243 0643 0268 0289 0689 02A2 0265 0266 0267
        0281 0243 0643 0281 0243 0643 0268 0263 0663 0245 0246 0247 02A2 0265 0266 0267
        0281 0243 0643 0281 0243 0643 0268 0243 0643 0285 0286 0287 02A2 0285 0286 0287
        0281 0263 0663 0281 0243 0643 0268 0243 064B 0241 0241 0241 0241 0241 0241 0241
        0281 0243 0643 0281 0243 0643 0268 066C 066B 0261 0261 0261 0261 0261 0261 0261
        02A3 0243 0643 02A3 0243 064B 0241 0241 0241 0241 0242 0241 0241 0241 028B 028C
        0281 0243 0643 0281 066C 066B 0261 0261 0261 0261 0262 0261 0261 0261 02AB 02AC
        0281 0243 0643 0281 0268 02A2 0245 0246 0246 0246 0246 0247 02A2 0268 0243 0643
        0281 0243 0643 0281 0268 02A2 0285 0286 0286 0264 0266 0267 02A2 0268 0243 0643
        0281 0243 0643 02A3 02A3 02A3 02A3 02A3 02A4 0265 0266 0267 02A2 0268 0263 0663
        0281 0243 0643 0281 0268 02A2 0245 0247 02A2 0265 0266 0267 02A2 0268 0243 0643
        00FF 0243 0643 0281 0268 02A2 0285 0287 02A2 0285 0286 0287 02A2 0268 0243 0643
        00FF 0243 0643 0282 0282 0283 0282 0282 02A2 0282 0282 0282 0282 0282 0243 0643
        02A3 0243 0643 02A3 02A3 02A3 02A3 02A3 02A2 02A3 02A3 02A3 02A3 02A3 0243 0643
        00FF 0243 0643 0281 0268 0282 0282 0282 02A2 0282 0283 0282 0282 0282 0243 0643
        00FF 0243 0643 0281 0268 02A2 0245 0247 02A2 0245 0246 0247 0284 02A3 0243 0643
      </Screen>
          <Screen X="2" Y="1">
        0281 0268 0281 0265 0266 0266 0248 0248 0267 0263 0663 0268 0243 0643 00FF 0268
        0281 0268 0281 0265 0266 0266 0266 0266 0267 0243 0643 06A4 02A3 02A3 02A3 02A3
        02A1 0268 0281 0285 0286 0286 0286 0286 0287 0243 0643 02A2 0243 0643 0268 0268
        0281 0242 0241 0241 0241 0241 028B 028C 0268 0243 0643 02A2 0243 0643 0268 0268
        0281 0262 0261 0261 0261 0261 02AB 02AC 0268 0243 0643 02A2 0243 0643 0268 0268
        0281 0245 0246 0246 0246 0247 0243 0643 0268 0243 0643 02A2 0243 0643 0268 0268
        02A1 0265 02A7 0266 0266 0267 0243 0643 0268 0243 0643 02A2 0243 0643 0268 0268
        0281 0265 0266 0266 0266 0267 0263 0663 0268 0243 0643 02A2 0243 0643 0268 0268
        0281 0285 0286 0264 02A8 0267 0243 0643 0268 0263 0663 02A2 0243 0643 0268 0268
        0281 0268 0281 0265 0266 0267 0243 0643 0268 0243 0643 02A2 0243 0643 0268 0268
        0281 0268 0281 0285 0286 0287 0243 0643 0268 0243 0643 02A2 0243 0643 0268 0268
        0281 0268 02A1 0268 06A4 02A3 0243 0643 02A3 0243 0643 02A2 02A3 02A3 02A3 02A3
        0281 0282 0282 0283 02A2 0282 0243 0643 0282 0243 0643 02A2 0282 0282 0282 0282
        0281 02A3 02A3 02A3 0684 0268 0243 0643 0268 0243 0643 02A2 0243 0643 0268 0268
        0281 0282 0283 0282 0282 0282 0243 0643 0282 0282 0282 0282 0282 0282 0282 0282
        0281 02A3 02A3 02A3 02A4 0268 0263 0663 0268 0243 0643 02A2 0243 0643 0268 0268
      </Screen>
          <Screen X="3" Y="1">
        0268 0268 00FF 0243 0643 0281 0281 0268 0268 0268 02A2 0268 0268 0268 00FF 00FF
        02A3 02A3 02A3 02A3 02A3 0281 0281 02A3 02A3 02A3 02A2 02A3 02A3 02A3 00FF 00FF
        0268 0268 0268 0243 0643 0281 0281 0245 0246 0247 02A2 0268 0268 0268 00FF 00FF
        0268 0268 0268 0243 0643 02A1 0281 0265 0266 0267 02A2 0268 0268 0268 00FF 00FF
        0268 0268 0268 0243 0643 0281 02A1 0265 0266 0267 0284 02A3 02A3 02A3 02A3 02A3
        0268 0268 0268 0263 0663 0281 0281 0285 0286 0287 0268 0268 0268 0268 0268 0268
        0268 0268 0268 0243 064B 0281 0281 0241 028A 0241 028B 028C 0245 0246 0246 0246
        0268 0268 0268 066C 066B 0281 0281 0261 02AA 0261 02AB 02AC 0265 02A9 02A9 0266
        0268 0268 0246 0246 0247 0281 0281 0245 0246 0247 0243 0643 0265 0266 0266 0266
        0268 0268 0266 0266 0267 0281 0281 0265 0266 0267 0243 0643 0285 0286 0286 0286
        0268 0268 0266 0266 0267 0281 0281 0265 0266 0267 0243 0643 0268 0268 0268 0268
        02A3 00FF 0266 0266 0267 0281 0281 0265 0266 0267 0243 0643 0268 0268 0268 0268
        0282 00FF 0266 0266 0267 0281 0281 0265 0266 0267 0243 0643 00FF 00FF 00FF 00FF
        0268 00FF 0A46 0A46 0E45 0281 0281 0A45 0A46 0E45 0243 0643 00FF 00FF 00FF 00FF
        0282 0282 0282 0282 0282 0282 0282 0282 0282 0282 0282 0282 0282 0282 0282 0282
        0268 00FF 00FF 00FF 0267 0281 0281 0265 0266 0267 0243 0643 00FF 00FF 00FF 00FF
      </Screen>
          <Screen X="0" Y="2">
        00FF 00FF 00FF 00FF 00FF 00FF 00FF 00FF 00FF 00FF 00FF 00FF 00FF 00FF 00FF 00FF
        00FF 00FF 00FF 00FF 00FF 00FF 00FF 00FF 00FF 00FF 00FF 00FF 00FF 00FF 00FF 0282
        00FF 00FF 00FF 00FF 00FF 00FF 00FF 00FF 00FF 00FF 00FF 00FF 00FF 00FF 00FF 00FF
        00FF 00FF 00FF 00FF 00FF 00FF 00FF 00FF 00FF 00FF 00FF 00FF 00FF 00FF 00FF 02A3
        00FF 00FF 00FF 00FF 00FF 00FF 00FF 00FF 00FF 00FF 00FF 00FF 00FF 00FF 00FF 00FF
        00FF 00FF 00FF 00FF 00FF 00FF 00FF 00FF 00FF 00FF 00FF 00FF 00FF 00FF 00FF 00FF
        00FF 00FF 00FF 00FF 00FF 00FF 00FF 00FF 00FF 00FF 00FF 00FF 00FF 00FF 00FF 00FF
        00FF 00FF 00FF 00FF 00FF 00FF 00FF 00FF 00FF 00FF 00FF 00FF 00FF 00FF 00FF 00FF
        00FF 00FF 00FF 00FF 00FF 00FF 00FF 00FF 00FF 00FF 00FF 00FF 00FF 00FF 00FF 00FF
        00FF 00FF 00FF 00FF 00FF 00FF 00FF 00FF 00FF 00FF 00FF 00FF 00FF 00FF 00FF 00FF
        00FF 00FF 00FF 00FF 00FF 00FF 00FF 00FF 00FF 00FF 00FF 00FF 00FF 00FF 00FF 00FF
        00FF 00FF 00FF 00FF 00FF 00FF 00FF 00FF 00FF 00FF 00FF 00FF 00FF 00FF 00FF 00FF
        00FF 00FF 00FF 00FF 00FF 00FF 00FF 00FF 00FF 00FF 00FF 00FF 00FF 00FF 00FF 00FF
        00FF 00FF 00FF 00FF 00FF 00FF 00FF 00FF 00FF 00FF 00FF 00FF 00FF 00FF 00FF 00FF
        00FF 00FF 00FF 00FF 00FF 00FF 00FF 00FF 00FF 00FF 00FF 00FF 00FF 00FF 00FF 00FF
        00FF 00FF 00FF 00FF 00FF 00FF 00FF 00FF 00FF 00FF 00FF 00FF 00FF 00FF 00FF 00FF
      </Screen>
          <Screen X="1" Y="2">
        00FF 0243 0643 0281 0268 02A2 0285 0287 02A2 0285 0286 0287 0268 0268 0243 0643
        0282 0243 0643 0282 0282 0282 0283 0282 0282 0282 0282 0283 0282 0282 0243 0643
        00FF 0243 0643 0281 0268 02A2 0268 0268 02A2 0245 0246 0246 0246 0247 0243 0643
        02A3 0243 0643 02A3 02A3 02A3 02A3 02A3 0684 0265 0266 0266 02A6 0267 0263 0663
        00FF 0263 0663 0281 0268 02A2 0268 0245 0246 0288 02A6 0266 0266 0267 0244 0644
        00FF 0243 0643 0281 0268 02A2 0268 0265 0266 0266 0266 0266 0248 0267 0243 0643
        00FF 0243 0643 0281 0268 02A2 0268 0265 0266 0266 0266 0266 0266 0267 0243 0643
        00FF 0243 0643 0281 0268 02A2 0268 0265 0266 0266 0266 0266 0266 0267 0243 0643
        00FF 0243 0643 0281 0268 02A2 0268 0285 0286 0286 0286 0286 0286 0287 0243 0643
        00FF 0263 0663 0241 0241 0241 0241 0241 0241 0241 0241 0241 0242 0241 0263 0663
        00FF 0243 0643 0261 0261 0261 0261 0261 0261 0261 0261 0261 0262 0261 0243 0643
        00FF 0243 0643 0281 0268 02A2 0245 0246 0246 0246 0246 0247 06A4 02A3 0243 0643
        00FF 0243 0643 0281 0268 02A2 0265 02A6 0266 0266 0266 0267 02A2 0268 0243 0643
        00FF 0243 0643 0281 0268 02A2 0265 0266 0266 02A5 0266 0267 02A2 0268 0243 0643
        00FF 0243 0643 0281 0268 02A2 0265 0266 0266 0AA5 0266 0267 02A2 0268 0243 0643
        00FF 00FF 00FF 00FF 00FF 00FF 00FF 00FF 00FF 00FF 00FF 00FF 00FF 00FF 00FF 00FF
      </Screen>
          <Screen X="2" Y="2">
        02A1 0268 0281 0268 02A2 0268 0243 0643 0268 0243 0643 02A2 0243 0643 0268 0268
        0281 0282 0245 0247 0284 02A3 0243 0643 02A3 0243 0643 02A2 02A3 02A3 02A3 02A3
        0281 0245 0288 0688 0246 0247 0243 064B 0241 0241 028A 0241 0241 0241 0241 0241
        0281 0265 0266 0266 0266 0267 066C 066B 0261 0261 02AA 0261 0261 0261 0261 0261
        0281 0265 0266 0266 02A6 0688 0246 0246 0247 0243 0643 02A2 0243 0643 0268 0268
        02A1 0265 0266 0266 0266 0266 0266 0266 0267 0243 0643 02A2 0243 0643 0268 0268
        0281 0265 02A7 02A9 0266 0664 0286 0286 0287 0243 0643 02A2 0243 0643 0268 0268
        0281 0285 0286 0286 0286 0287 068C 068B 0241 0243 0643 02A2 0242 0241 0241 0241
        0281 0268 0268 0268 0268 0268 06AC 06AB 0261 0263 0663 02A2 0262 0261 0261 0261
        0281 0241 0241 028A 0241 0241 024B 0643 0268 0243 0643 02A2 0243 0643 0268 0268
        0281 0261 0261 02AA 0261 0261 026B 026C 0268 0243 0643 02A2 0243 0643 0268 0268
        0281 02A3 02A3 02A3 02A3 02A3 02A3 02A3 02A3 0243 0643 02A2 02A3 02A3 02A3 02A3
        0281 0245 0246 0246 0246 0246 0247 0245 0247 0243 0643 02A2 0243 0643 0268 0268
        0281 0265 0266 0266 0266 0266 0267 0265 0267 0243 0643 02A2 0243 0643 0268 0268
        00FF 00FF 00FF 00FF 00FF 00FF 00FF 00FF 00FF 00FF 00FF 00FF 00FF 00FF 00FF 00FF
        00FF 00FF 00FF 00FF 00FF 00FF 00FF 00FF 00FF 00FF 00FF 00FF 00FF 00FF 00FF 00FF
      </Screen>
          <Screen X="3" Y="2">
        0268 00FF 00FF 00FF 00FF 00FF 00FF 00FF 00FF 00FF 00FF 00FF 00FF 00FF 00FF 00FF
        02A3 00FF 00FF 00FF 00FF 00FF 00FF 00FF 00FF 00FF 00FF 00FF 00FF 00FF 00FF 00FF
        0241 0241 00FF 00FF 00FF 00FF 00FF 00FF 00FF 00FF 00FF 00FF 00FF 00FF 00FF 00FF
        0261 0261 00FF 00FF 00FF 00FF 00FF 00FF 00FF 00FF 00FF 00FF 00FF 00FF 00FF 00FF
        00FF 00FF 00FF 00FF 00FF 00FF 00FF 00FF 00FF 00FF 00FF 00FF 00FF 00FF 00FF 00FF
        00FF 00FF 00FF 00FF 00FF 00FF 00FF 00FF 00FF 00FF 00FF 00FF 00FF 00FF 00FF 00FF
        00FF 00FF 00FF 00FF 00FF 00FF 00FF 00FF 00FF 00FF 00FF 00FF 00FF 00FF 00FF 00FF
        00FF 00FF 00FF 00FF 00FF 00FF 00FF 00FF 00FF 00FF 00FF 00FF 00FF 00FF 00FF 00FF
        00FF 00FF 00FF 00FF 00FF 00FF 00FF 00FF 00FF 00FF 00FF 00FF 00FF 00FF 00FF 00FF
        00FF 00FF 00FF 00FF 00FF 00FF 00FF 00FF 00FF 00FF 00FF 00FF 00FF 00FF 00FF 00FF
        00FF 00FF 00FF 00FF 00FF 00FF 00FF 00FF 00FF 00FF 00FF 00FF 00FF 00FF 00FF 00FF
        00FF 00FF 00FF 00FF 00FF 00FF 00FF 00FF 00FF 00FF 00FF 00FF 00FF 00FF 00FF 00FF
        00FF 00FF 00FF 00FF 00FF 00FF 00FF 00FF 00FF 00FF 00FF 00FF 00FF 00FF 00FF 00FF
        00FF 00FF 00FF 00FF 00FF 00FF 00FF 00FF 00FF 00FF 00FF 00FF 00FF 00FF 00FF 00FF
        00FF 00FF 00FF 00FF 00FF 00FF 00FF 00FF 00FF 00FF 00FF 00FF 00FF 00FF 00FF 00FF
        00FF 00FF 00FF 00FF 00FF 00FF 00FF 00FF 00FF 00FF 00FF 00FF 00FF 00FF 00FF 00FF
      </Screen>
        </Layer2>
      </LevelData>
      <GFXset>21</GFXset>
      <music>0000</music>
      <FX1s>
        <FX1 default="true">
          <surfacestart>01B8</surfacestart>
          <surfacenew>FFFF</surfacenew>
          <surfacespeed>0000</surfacespeed>
          <surfacedelay>00</surfacedelay>
          <type>02</type>
          <transparency1_A>02</transparency1_A>
          <transparency2_B>02</transparency2_B>
          <liquidflags_C>03</liquidflags_C>
          <paletteflags>05</paletteflags>
          <animationflags>00</animationflags>
          <paletteblend>02</paletteblend>
        </FX1>
      </FX1s>
      <Enemies killcount="00">
        <Enemy>
          <ID>E8FF</ID>
          <X>0378</X>
          <Y>0180</Y>
          <tilemap>0000</tilemap>
          <special>2800</special>
          <gfx>0000</gfx>
          <speed>0000</speed>
          <speed2>0000</speed2>
        </Enemy>
        <Enemy>
          <ID>FA80</ID>
          <X>0198</X>
          <Y>02A8</Y>
          <tilemap>0000</tilemap>
          <special>2000</special>
          <gfx>0000</gfx>
          <speed>0102</speed>
          <speed2>010C</speed2>
        </Enemy>
        <Enemy>
          <ID>F6D3</ID>
          <X>0078</X>
          <Y>0140</Y>
          <tilemap>0000</tilemap>
          <special>2000</special>
          <gfx>0004</gfx>
          <speed>8001</speed>
          <speed2>0090</speed2>
        </Enemy>
      </Enemies>
      <EnemyTypes>
        <Enemy>
          <GFX>E8FF</GFX>
          <palette>0001</palette>
        </Enemy>
        <Enemy>
          <GFX>F6D3</GFX>
          <palette>0002</palette>
        </Enemy>
        <Enemy>
          <GFX>FA80</GFX>
          <palette>0007</palette>
        </Enemy>
      </EnemyTypes>
      <layer2_type>Layer2</layer2_type>
      <layer2_xscroll>00</layer2_xscroll>
      <layer2_yscroll>00</layer2_yscroll>
      <ScrollData const="0001" />
      <roomvar>0000</roomvar>
      <FX2>0000</FX2>
      <PLMs>
        <PLM>
          <type>FE90</type>
          <x>1E</x>
          <y>00</y>
          <arg>0003</arg>
        </PLM>
      </PLMs>
      <BGData />
      <layer1_2>91D3</layer1_2>
    </State>
  </States>
</Room>